[{"id":"city:waterloo:sierra-leone:2403094","name":"Waterloo","normalizedName":"waterloo","country":"Sierra Leone","normalizedCountry":"sierra-leone","subcountry":"Western Area","geonameid":"2403094","cityStatus":"index_only","hasCoordinates":false,"isOfficialNetworkNode":false,"isE2EHub":false,"hubCandidate":false,"isDuplicate":false},{"id":"city:segbwema:sierra-leone:2404041","name":"Segbwema","normalizedName":"segbwema","country":"Sierra Leone","normalizedCountry":"sierra-leone","subcountry":"Eastern Province","geonameid":"2404041","cityStatus":"index_only","hasCoordinates":false,"isOfficialNetworkNode":false,"isE2EHub":false,"hubCandidate":false,"isDuplicate":false},{"id":"city:port-loko:sierra-leone:2404433","name":"Port Loko","normalizedName":"port-loko","country":"Sierra Leone","normalizedCountry":"sierra-leone","subcountry":"North West","geonameid":"2404433","cityStatus":"index_only","hasCoordinates":false,"isOfficialNetworkNode":false,"isE2EHub":false,"hubCandidate":false,"isDuplicate":false},{"id":"city:njala:sierra-leone:2404837","name":"Njala","normalizedName":"njala","country":"Sierra Leone","normalizedCountry":"sierra-leone","subcountry":"Southern Province","geonameid":"2404837","cityStatus":"index_only","hasCoordinates":false,"isOfficialNetworkNode":false,"isE2EHub":false,"hubCandidate":false,"isDuplicate":false},{"id":"city:makeni:sierra-leone:2406407","name":"Makeni","normalizedName":"makeni","country":"Sierra Leone","normalizedCountry":"sierra-leone","subcountry":"Northern Province","geonameid":"2406407","cityStatus":"index_only","hasCoordinates":false,"isOfficialNetworkNode":false,"isE2EHub":false,"hubCandidate":false,"isDuplicate":false},{"id":"city:lunsar:sierra-leone:2406916","name":"Lunsar","normalizedName":"lunsar","country":"Sierra Leone","normalizedCountry":"sierra-leone","subcountry":"Northern Province","geonameid":"2406916","cityStatus":"index_only","hasCoordinates":false,"isOfficialNetworkNode":false,"isE2EHub":false,"hubCandidate":false,"isDuplicate":false},{"id":"city:koidu:sierra-leone:2407656","name":"Koidu","normalizedName":"koidu","country":"Sierra Leone","normalizedCountry":"sierra-leone","subcountry":"Eastern Province","geonameid":"2407656","cityStatus":"index_only","hasCoordinates":false,"isOfficialNetworkNode":false,"isE2EHub":false,"hubCandidate":false,"isDuplicate":false},{"id":"city:kenema:sierra-leone:2407790","name":"Kenema","normalizedName":"kenema","country":"Sierra Leone","normalizedCountry":"sierra-leone","subcountry":"Eastern Province","geonameid":"2407790","cityStatus":"index_only","hasCoordinates":false,"isOfficialNetworkNode":false,"isE2EHub":false,"hubCandidate":false,"isDuplicate":false},{"id":"city:kabala:sierra-leone:2408329","name":"Kabala","normalizedName":"kabala","country":"Sierra Leone","normalizedCountry":"sierra-leone","subcountry":"Northern Province","geonameid":"2408329","cityStatus":"index_only","hasCoordinates":false,"isOfficialNetworkNode":false,"isE2EHub":false,"hubCandidate":false,"isDuplicate":false},{"id":"city:freetown:sierra-leone:2409306","name":"Freetown","normalizedName":"freetown","country":"Sierra Leone","normalizedCountry":"sierra-leone","subcountry":"Western Area","geonameid":"2409306","cityStatus":"index_only","hasCoordinates":false,"isOfficialNetworkNode":false,"isE2EHub":false,"hubCandidate":false,"isDuplicate":false},{"id":"city:bumpe:sierra-leone:2409823","name":"Bumpe","normalizedName":"bumpe","country":"Sierra Leone","normalizedCountry":"sierra-leone","subcountry":"Southern Province","geonameid":"2409823","cityStatus":"index_only","hasCoordinates":false,"isOfficialNetworkNode":false,"isE2EHub":false,"hubCandidate":false,"isDuplicate":false},{"id":"city:bo:sierra-leone:2410048","name":"Bo","normalizedName":"bo","country":"Sierra Leone","normalizedCountry":"sierra-leone","subcountry":"Southern Province","geonameid":"2410048","cityStatus":"index_only","hasCoordinates":false,"isOfficialNetworkNode":false,"isE2EHub":false,"hubCandidate":false,"isDuplicate":false},{"id":"city:goderich:sierra-leone:9191693","name":"Goderich","normalizedName":"goderich","country":"Sierra Leone","normalizedCountry":"sierra-leone","subcountry":"Western Area","geonameid":"9191693","cityStatus":"index_only","hasCoordinates":false,"isOfficialNetworkNode":false,"isE2EHub":false,"hubCandidate":false,"isDuplicate":false},{"id":"city:mile-91:sierra-leone:12718740","name":"Mile 91","normalizedName":"mile-91","country":"Sierra Leone","normalizedCountry":"sierra-leone","subcountry":"Northern Province","geonameid":"12718740","cityStatus":"index_only","hasCoordinates":false,"isOfficialNetworkNode":false,"isE2EHub":false,"hubCandidate":false,"isDuplicate":false}]