[{"id":"city:yacuiba:bolivia-plurinational-state-of:3901178","name":"Yacuiba","normalizedName":"yacuiba","country":"Bolivia, Plurinational State of","normalizedCountry":"bolivia-plurinational-state-of","subcountry":"Tarija Department","geonameid":"3901178","cityStatus":"index_only","hasCoordinates":false,"isOfficialNetworkNode":false,"isE2EHub":false,"hubCandidate":false,"isDuplicate":false},{"id":"city:warnes:bolivia-plurinational-state-of:3901301","name":"Warnes","normalizedName":"warnes","country":"Bolivia, Plurinational State of","normalizedCountry":"bolivia-plurinational-state-of","subcountry":"Santa Cruz Department","geonameid":"3901301","cityStatus":"index_only","hasCoordinates":false,"isOfficialNetworkNode":false,"isE2EHub":false,"hubCandidate":false,"isDuplicate":false},{"id":"city:vinto:bolivia-plurinational-state-of:3901435","name":"Vinto","normalizedName":"vinto","country":"Bolivia, Plurinational State of","normalizedCountry":"bolivia-plurinational-state-of","subcountry":"Cochabamba","geonameid":"3901435","cityStatus":"index_only","hasCoordinates":false,"isOfficialNetworkNode":false,"isE2EHub":false,"hubCandidate":false,"isDuplicate":false},{"id":"city:villaz-n:bolivia-plurinational-state-of:3901501","name":"Villaz\u00f3n","normalizedName":"villaz-n","country":"Bolivia, Plurinational State of","normalizedCountry":"bolivia-plurinational-state-of","subcountry":"Potosi Department","geonameid":"3901501","cityStatus":"index_only","hasCoordinates":false,"isOfficialNetworkNode":false,"isE2EHub":false,"hubCandidate":false,"isDuplicate":false},{"id":"city:villa-yapacan:bolivia-plurinational-state-of:3901504","name":"Villa Yapacan\u00ed","normalizedName":"villa-yapacan","country":"Bolivia, Plurinational State of","normalizedCountry":"bolivia-plurinational-state-of","subcountry":"Santa Cruz Department","geonameid":"3901504","cityStatus":"index_only","hasCoordinates":false,"isOfficialNetworkNode":false,"isE2EHub":false,"hubCandidate":false,"isDuplicate":false},{"id":"city:villamontes:bolivia-plurinational-state-of:3901547","name":"Villamontes","normalizedName":"villamontes","country":"Bolivia, Plurinational State of","normalizedCountry":"bolivia-plurinational-state-of","subcountry":"Tarija Department","geonameid":"3901547","cityStatus":"index_only","hasCoordinates":false,"isOfficialNetworkNode":false,"isE2EHub":false,"hubCandidate":false,"isDuplicate":false},{"id":"city:viacha:bolivia-plurinational-state-of:3901742","name":"Viacha","normalizedName":"viacha","country":"Bolivia, Plurinational State of","normalizedCountry":"bolivia-plurinational-state-of","subcountry":"La Paz Department","geonameid":"3901742","cityStatus":"index_only","hasCoordinates":false,"isOfficialNetworkNode":false,"isE2EHub":false,"hubCandidate":false,"isDuplicate":false},{"id":"city:tupiza:bolivia-plurinational-state-of:3902202","name":"Tupiza","normalizedName":"tupiza","country":"Bolivia, Plurinational State of","normalizedCountry":"bolivia-plurinational-state-of","subcountry":"Potosi Department","geonameid":"3902202","cityStatus":"index_only","hasCoordinates":false,"isOfficialNetworkNode":false,"isE2EHub":false,"hubCandidate":false,"isDuplicate":false},{"id":"city:trinidad:bolivia-plurinational-state-of:3902377","name":"Trinidad","normalizedName":"trinidad","country":"Bolivia, Plurinational State of","normalizedCountry":"bolivia-plurinational-state-of","subcountry":"Beni Department","geonameid":"3902377","cityStatus":"index_only","hasCoordinates":false,"isOfficialNetworkNode":false,"isE2EHub":false,"hubCandidate":false,"isDuplicate":false},{"id":"city:tiquipaya:bolivia-plurinational-state-of:3902949","name":"Tiquipaya","normalizedName":"tiquipaya","country":"Bolivia, Plurinational State of","normalizedCountry":"bolivia-plurinational-state-of","subcountry":"Cochabamba","geonameid":"3902949","cityStatus":"index_only","hasCoordinates":false,"isOfficialNetworkNode":false,"isE2EHub":false,"hubCandidate":false,"isDuplicate":false},{"id":"city:tarija:bolivia-plurinational-state-of:3903320","name":"Tarija","normalizedName":"tarija","country":"Bolivia, Plurinational State of","normalizedCountry":"bolivia-plurinational-state-of","subcountry":"Tarija Department","geonameid":"3903320","cityStatus":"index_only","hasCoordinates":false,"isOfficialNetworkNode":false,"isE2EHub":false,"hubCandidate":false,"isDuplicate":false},{"id":"city:sucre:bolivia-plurinational-state-of:3903987","name":"Sucre","normalizedName":"sucre","country":"Bolivia, Plurinational State of","normalizedCountry":"bolivia-plurinational-state-of","subcountry":"Chuquisaca Department","geonameid":"3903987","cityStatus":"index_only","hasCoordinates":false,"isOfficialNetworkNode":false,"isE2EHub":false,"hubCandidate":false,"isDuplicate":false},{"id":"city:sipe-sipe:bolivia-plurinational-state-of:3904221","name":"Sipe Sipe","normalizedName":"sipe-sipe","country":"Bolivia, Plurinational State of","normalizedCountry":"bolivia-plurinational-state-of","subcountry":"Cochabamba","geonameid":"3904221","cityStatus":"index_only","hasCoordinates":false,"isOfficialNetworkNode":false,"isE2EHub":false,"hubCandidate":false,"isDuplicate":false},{"id":"city:el-torno:bolivia-plurinational-state-of:3904666","name":"El Torno","normalizedName":"el-torno","country":"Bolivia, Plurinational State of","normalizedCountry":"bolivia-plurinational-state-of","subcountry":"Santa Cruz Department","geonameid":"3904666","cityStatus":"index_only","hasCoordinates":false,"isOfficialNetworkNode":false,"isE2EHub":false,"hubCandidate":false,"isDuplicate":false},{"id":"city:santa-cruz-de-la-sierra:bolivia-plurinational-state-of:3904906","name":"Santa Cruz de la Sierra","normalizedName":"santa-cruz-de-la-sierra","country":"Bolivia, Plurinational State of","normalizedCountry":"bolivia-plurinational-state-of","subcountry":"Santa Cruz Department","geonameid":"3904906","cityStatus":"index_only","hasCoordinates":false,"isOfficialNetworkNode":false,"isE2EHub":false,"hubCandidate":false,"isDuplicate":false},{"id":"city:san-ignacio-de-velasco:bolivia-plurinational-state-of:3905658","name":"San Ignacio de Velasco","normalizedName":"san-ignacio-de-velasco","country":"Bolivia, Plurinational State of","normalizedCountry":"bolivia-plurinational-state-of","subcountry":"Santa Cruz Department","geonameid":"3905658","cityStatus":"index_only","hasCoordinates":false,"isOfficialNetworkNode":false,"isE2EHub":false,"hubCandidate":false,"isDuplicate":false},{"id":"city:sacaba:bolivia-plurinational-state-of:3906194","name":"Sacaba","normalizedName":"sacaba","country":"Bolivia, Plurinational State of","normalizedCountry":"bolivia-plurinational-state-of","subcountry":"Cochabamba","geonameid":"3906194","cityStatus":"index_only","hasCoordinates":false,"isOfficialNetworkNode":false,"isE2EHub":false,"hubCandidate":false,"isDuplicate":false},{"id":"city:riberalta:bolivia-plurinational-state-of:3906466","name":"Riberalta","normalizedName":"riberalta","country":"Bolivia, Plurinational State of","normalizedCountry":"bolivia-plurinational-state-of","subcountry":"Beni Department","geonameid":"3906466","cityStatus":"index_only","hasCoordinates":false,"isOfficialNetworkNode":false,"isE2EHub":false,"hubCandidate":false,"isDuplicate":false},{"id":"city:quillacollo:bolivia-plurinational-state-of:3906791","name":"Quillacollo","normalizedName":"quillacollo","country":"Bolivia, Plurinational State of","normalizedCountry":"bolivia-plurinational-state-of","subcountry":"Cochabamba","geonameid":"3906791","cityStatus":"index_only","hasCoordinates":false,"isOfficialNetworkNode":false,"isE2EHub":false,"hubCandidate":false,"isDuplicate":false},{"id":"city:punata:bolivia-plurinational-state-of:3907080","name":"Punata","normalizedName":"punata","country":"Bolivia, Plurinational State of","normalizedCountry":"bolivia-plurinational-state-of","subcountry":"Cochabamba","geonameid":"3907080","cityStatus":"index_only","hasCoordinates":false,"isOfficialNetworkNode":false,"isE2EHub":false,"hubCandidate":false,"isDuplicate":false},{"id":"city:potos:bolivia-plurinational-state-of:3907584","name":"Potos\u00ed","normalizedName":"potos","country":"Bolivia, Plurinational State of","normalizedCountry":"bolivia-plurinational-state-of","subcountry":"Potosi Department","geonameid":"3907584","cityStatus":"index_only","hasCoordinates":false,"isOfficialNetworkNode":false,"isE2EHub":false,"hubCandidate":false,"isDuplicate":false},{"id":"city:oruro:bolivia-plurinational-state-of:3909234","name":"Oruro","normalizedName":"oruro","country":"Bolivia, Plurinational State of","normalizedCountry":"bolivia-plurinational-state-of","subcountry":"Oruro","geonameid":"3909234","cityStatus":"index_only","hasCoordinates":false,"isOfficialNetworkNode":false,"isE2EHub":false,"hubCandidate":false,"isDuplicate":false},{"id":"city:montero:bolivia-plurinational-state-of:3910027","name":"Montero","normalizedName":"montero","country":"Bolivia, Plurinational State of","normalizedCountry":"bolivia-plurinational-state-of","subcountry":"Santa Cruz Department","geonameid":"3910027","cityStatus":"index_only","hasCoordinates":false,"isOfficialNetworkNode":false,"isE2EHub":false,"hubCandidate":false,"isDuplicate":false},{"id":"city:mizque:bolivia-plurinational-state-of:3910291","name":"Mizque","normalizedName":"mizque","country":"Bolivia, Plurinational State of","normalizedCountry":"bolivia-plurinational-state-of","subcountry":"Cochabamba","geonameid":"3910291","cityStatus":"index_only","hasCoordinates":false,"isOfficialNetworkNode":false,"isE2EHub":false,"hubCandidate":false,"isDuplicate":false},{"id":"city:llallagua:bolivia-plurinational-state-of:3911409","name":"Llallagua","normalizedName":"llallagua","country":"Bolivia, Plurinational State of","normalizedCountry":"bolivia-plurinational-state-of","subcountry":"Potosi Department","geonameid":"3911409","cityStatus":"index_only","hasCoordinates":false,"isOfficialNetworkNode":false,"isE2EHub":false,"hubCandidate":false,"isDuplicate":false},{"id":"city:la-paz:bolivia-plurinational-state-of:3911925","name":"La Paz","normalizedName":"la-paz","country":"Bolivia, Plurinational State of","normalizedCountry":"bolivia-plurinational-state-of","subcountry":"La Paz Department","geonameid":"3911925","cityStatus":"candidate","hasCoordinates":true,"isOfficialNetworkNode":false,"isE2EHub":false,"hubCandidate":true,"isDuplicate":false},{"id":"city:laja:bolivia-plurinational-state-of:3912103","name":"Laja","normalizedName":"laja","country":"Bolivia, Plurinational State of","normalizedCountry":"bolivia-plurinational-state-of","subcountry":"La Paz Department","geonameid":"3912103","cityStatus":"index_only","hasCoordinates":false,"isOfficialNetworkNode":false,"isE2EHub":false,"hubCandidate":false,"isDuplicate":false},{"id":"city:huanuni:bolivia-plurinational-state-of:3914839","name":"Huanuni","normalizedName":"huanuni","country":"Bolivia, Plurinational State of","normalizedCountry":"bolivia-plurinational-state-of","subcountry":"Oruro","geonameid":"3914839","cityStatus":"index_only","hasCoordinates":false,"isOfficialNetworkNode":false,"isE2EHub":false,"hubCandidate":false,"isDuplicate":false},{"id":"city:guayaramer-n:bolivia-plurinational-state-of:3915350","name":"Guayaramer\u00edn","normalizedName":"guayaramer-n","country":"Bolivia, Plurinational State of","normalizedCountry":"bolivia-plurinational-state-of","subcountry":"Beni Department","geonameid":"3915350","cityStatus":"index_only","hasCoordinates":false,"isOfficialNetworkNode":false,"isE2EHub":false,"hubCandidate":false,"isDuplicate":false},{"id":"city:cotoca:bolivia-plurinational-state-of:3918937","name":"Cotoca","normalizedName":"cotoca","country":"Bolivia, Plurinational State of","normalizedCountry":"bolivia-plurinational-state-of","subcountry":"Santa Cruz Department","geonameid":"3918937","cityStatus":"index_only","hasCoordinates":false,"isOfficialNetworkNode":false,"isE2EHub":false,"hubCandidate":false,"isDuplicate":false},{"id":"city:colcapirhua:bolivia-plurinational-state-of:3919902","name":"Colcapirhua","normalizedName":"colcapirhua","country":"Bolivia, Plurinational State of","normalizedCountry":"bolivia-plurinational-state-of","subcountry":"Cochabamba","geonameid":"3919902","cityStatus":"index_only","hasCoordinates":false,"isOfficialNetworkNode":false,"isE2EHub":false,"hubCandidate":false,"isDuplicate":false},{"id":"city:cochabamba:bolivia-plurinational-state-of:3919968","name":"Cochabamba","normalizedName":"cochabamba","country":"Bolivia, Plurinational State of","normalizedCountry":"bolivia-plurinational-state-of","subcountry":"Cochabamba","geonameid":"3919968","cityStatus":"index_only","hasCoordinates":false,"isOfficialNetworkNode":false,"isE2EHub":false,"hubCandidate":false,"isDuplicate":false},{"id":"city:cobija:bolivia-plurinational-state-of:3919998","name":"Cobija","normalizedName":"cobija","country":"Bolivia, Plurinational State of","normalizedCountry":"bolivia-plurinational-state-of","subcountry":"Pando","geonameid":"3919998","cityStatus":"index_only","hasCoordinates":false,"isOfficialNetworkNode":false,"isE2EHub":false,"hubCandidate":false,"isDuplicate":false},{"id":"city:caranavi:bolivia-plurinational-state-of:3922037","name":"Caranavi","normalizedName":"caranavi","country":"Bolivia, Plurinational State of","normalizedCountry":"bolivia-plurinational-state-of","subcountry":"La Paz Department","geonameid":"3922037","cityStatus":"index_only","hasCoordinates":false,"isOfficialNetworkNode":false,"isE2EHub":false,"hubCandidate":false,"isDuplicate":false},{"id":"city:camiri:bolivia-plurinational-state-of:3922414","name":"Camiri","normalizedName":"camiri","country":"Bolivia, Plurinational State of","normalizedCountry":"bolivia-plurinational-state-of","subcountry":"Santa Cruz Department","geonameid":"3922414","cityStatus":"index_only","hasCoordinates":false,"isOfficialNetworkNode":false,"isE2EHub":false,"hubCandidate":false,"isDuplicate":false},{"id":"city:bermejo:bolivia-plurinational-state-of:3923154","name":"Bermejo","normalizedName":"bermejo","country":"Bolivia, Plurinational State of","normalizedCountry":"bolivia-plurinational-state-of","subcountry":"Tarija Department","geonameid":"3923154","cityStatus":"index_only","hasCoordinates":false,"isOfficialNetworkNode":false,"isE2EHub":false,"hubCandidate":false,"isDuplicate":false},{"id":"city:achocalla:bolivia-plurinational-state-of:3924569","name":"Achocalla","normalizedName":"achocalla","country":"Bolivia, Plurinational State of","normalizedCountry":"bolivia-plurinational-state-of","subcountry":"La Paz Department","geonameid":"3924569","cityStatus":"index_only","hasCoordinates":false,"isOfficialNetworkNode":false,"isE2EHub":false,"hubCandidate":false,"isDuplicate":false},{"id":"city:ascenci-n-de-guarayos:bolivia-plurinational-state-of:9129422","name":"Ascenci\u00f3n de Guarayos","normalizedName":"ascenci-n-de-guarayos","country":"Bolivia, Plurinational State of","normalizedCountry":"bolivia-plurinational-state-of","subcountry":"Santa Cruz Department","geonameid":"9129422","cityStatus":"index_only","hasCoordinates":false,"isOfficialNetworkNode":false,"isE2EHub":false,"hubCandidate":false,"isDuplicate":false},{"id":"city:san-borja:bolivia-plurinational-state-of:11467676","name":"San Borja","normalizedName":"san-borja","country":"Bolivia, Plurinational State of","normalizedCountry":"bolivia-plurinational-state-of","subcountry":"Beni Department","geonameid":"11467676","cityStatus":"index_only","hasCoordinates":false,"isOfficialNetworkNode":false,"isE2EHub":false,"hubCandidate":false,"isDuplicate":false}]