[{"id":"city:zwijndrecht:belgium:2783081","name":"Zwijndrecht","normalizedName":"zwijndrecht","country":"Belgium","normalizedCountry":"belgium","subcountry":"Flanders","geonameid":"2783081","cityStatus":"index_only","hasCoordinates":false,"isOfficialNetworkNode":false,"isE2EHub":false,"hubCandidate":false,"isDuplicate":false},{"id":"city:zwevegem:belgium:2783089","name":"Zwevegem","normalizedName":"zwevegem","country":"Belgium","normalizedCountry":"belgium","subcountry":"Flanders","geonameid":"2783089","cityStatus":"index_only","hasCoordinates":false,"isOfficialNetworkNode":false,"isE2EHub":false,"hubCandidate":false,"isDuplicate":false},{"id":"city:zottegem:belgium:2783175","name":"Zottegem","normalizedName":"zottegem","country":"Belgium","normalizedCountry":"belgium","subcountry":"Flanders","geonameid":"2783175","cityStatus":"index_only","hasCoordinates":false,"isOfficialNetworkNode":false,"isE2EHub":false,"hubCandidate":false,"isDuplicate":false},{"id":"city:zonhoven:belgium:2783188","name":"Zonhoven","normalizedName":"zonhoven","country":"Belgium","normalizedCountry":"belgium","subcountry":"Flanders","geonameid":"2783188","cityStatus":"index_only","hasCoordinates":false,"isOfficialNetworkNode":false,"isE2EHub":false,"hubCandidate":false,"isDuplicate":false},{"id":"city:zolder:belgium:2783197","name":"Zolder","normalizedName":"zolder","country":"Belgium","normalizedCountry":"belgium","subcountry":"Flanders","geonameid":"2783197","cityStatus":"index_only","hasCoordinates":false,"isOfficialNetworkNode":false,"isE2EHub":false,"hubCandidate":false,"isDuplicate":false},{"id":"city:zemst:belgium:2783274","name":"Zemst","normalizedName":"zemst","country":"Belgium","normalizedCountry":"belgium","subcountry":"Flanders","geonameid":"2783274","cityStatus":"index_only","hasCoordinates":false,"isOfficialNetworkNode":false,"isE2EHub":false,"hubCandidate":false,"isDuplicate":false},{"id":"city:zele:belgium:2783293","name":"Zele","normalizedName":"zele","country":"Belgium","normalizedCountry":"belgium","subcountry":"Flanders","geonameid":"2783293","cityStatus":"index_only","hasCoordinates":false,"isOfficialNetworkNode":false,"isE2EHub":false,"hubCandidate":false,"isDuplicate":false},{"id":"city:zedelgem:belgium:2783308","name":"Zedelgem","normalizedName":"zedelgem","country":"Belgium","normalizedCountry":"belgium","subcountry":"Flanders","geonameid":"2783308","cityStatus":"index_only","hasCoordinates":false,"isOfficialNetworkNode":false,"isE2EHub":false,"hubCandidate":false,"isDuplicate":false},{"id":"city:zaventem:belgium:2783310","name":"Zaventem","normalizedName":"zaventem","country":"Belgium","normalizedCountry":"belgium","subcountry":"Flanders","geonameid":"2783310","cityStatus":"index_only","hasCoordinates":false,"isOfficialNetworkNode":false,"isE2EHub":false,"hubCandidate":false,"isDuplicate":false},{"id":"city:wondelgem:belgium:2783456","name":"Wondelgem","normalizedName":"wondelgem","country":"Belgium","normalizedCountry":"belgium","subcountry":"Flanders","geonameid":"2783456","cityStatus":"index_only","hasCoordinates":false,"isOfficialNetworkNode":false,"isE2EHub":false,"hubCandidate":false,"isDuplicate":false},{"id":"city:woluwe-saint-lambert:belgium:2783476","name":"Woluwe-Saint-Lambert","normalizedName":"woluwe-saint-lambert","country":"Belgium","normalizedCountry":"belgium","subcountry":"Brussels Capital","geonameid":"2783476","cityStatus":"index_only","hasCoordinates":false,"isOfficialNetworkNode":false,"isE2EHub":false,"hubCandidate":false,"isDuplicate":false},{"id":"city:wilrijk:belgium:2783615","name":"Wilrijk","normalizedName":"wilrijk","country":"Belgium","normalizedCountry":"belgium","subcountry":"Flanders","geonameid":"2783615","cityStatus":"index_only","hasCoordinates":false,"isOfficialNetworkNode":false,"isE2EHub":false,"hubCandidate":false,"isDuplicate":false},{"id":"city:willebroek:belgium:2783632","name":"Willebroek","normalizedName":"willebroek","country":"Belgium","normalizedCountry":"belgium","subcountry":"Flanders","geonameid":"2783632","cityStatus":"index_only","hasCoordinates":false,"isOfficialNetworkNode":false,"isE2EHub":false,"hubCandidate":false,"isDuplicate":false},{"id":"city:wevelgem:belgium:2783759","name":"Wevelgem","normalizedName":"wevelgem","country":"Belgium","normalizedCountry":"belgium","subcountry":"Flanders","geonameid":"2783759","cityStatus":"index_only","hasCoordinates":false,"isOfficialNetworkNode":false,"isE2EHub":false,"hubCandidate":false,"isDuplicate":false},{"id":"city:wetteren:belgium:2783763","name":"Wetteren","normalizedName":"wetteren","country":"Belgium","normalizedCountry":"belgium","subcountry":"Flanders","geonameid":"2783763","cityStatus":"index_only","hasCoordinates":false,"isOfficialNetworkNode":false,"isE2EHub":false,"hubCandidate":false,"isDuplicate":false},{"id":"city:westerlo:belgium:2783801","name":"Westerlo","normalizedName":"westerlo","country":"Belgium","normalizedCountry":"belgium","subcountry":"Flanders","geonameid":"2783801","cityStatus":"index_only","hasCoordinates":false,"isOfficialNetworkNode":false,"isE2EHub":false,"hubCandidate":false,"isDuplicate":false},{"id":"city:wervik:belgium:2783820","name":"Wervik","normalizedName":"wervik","country":"Belgium","normalizedCountry":"belgium","subcountry":"Flanders","geonameid":"2783820","cityStatus":"index_only","hasCoordinates":false,"isOfficialNetworkNode":false,"isE2EHub":false,"hubCandidate":false,"isDuplicate":false},{"id":"city:wavre:belgium:2783941","name":"Wavre","normalizedName":"wavre","country":"Belgium","normalizedCountry":"belgium","subcountry":"Wallonia","geonameid":"2783941","cityStatus":"index_only","hasCoordinates":false,"isOfficialNetworkNode":false,"isE2EHub":false,"hubCandidate":false,"isDuplicate":false},{"id":"city:watermael-boitsfort:belgium:2783979","name":"Watermael-Boitsfort","normalizedName":"watermael-boitsfort","country":"Belgium","normalizedCountry":"belgium","subcountry":"Brussels Capital","geonameid":"2783979","cityStatus":"index_only","hasCoordinates":false,"isOfficialNetworkNode":false,"isE2EHub":false,"hubCandidate":false,"isDuplicate":false},{"id":"city:waterloo:belgium:2783985","name":"Waterloo","normalizedName":"waterloo","country":"Belgium","normalizedCountry":"belgium","subcountry":"Wallonia","geonameid":"2783985","cityStatus":"index_only","hasCoordinates":false,"isOfficialNetworkNode":false,"isE2EHub":false,"hubCandidate":false,"isDuplicate":false},{"id":"city:waregem:belgium:2784068","name":"Waregem","normalizedName":"waregem","country":"Belgium","normalizedCountry":"belgium","subcountry":"Flanders","geonameid":"2784068","cityStatus":"index_only","hasCoordinates":false,"isOfficialNetworkNode":false,"isE2EHub":false,"hubCandidate":false,"isDuplicate":false},{"id":"city:walcourt:belgium:2784189","name":"Walcourt","normalizedName":"walcourt","country":"Belgium","normalizedCountry":"belgium","subcountry":"Wallonia","geonameid":"2784189","cityStatus":"index_only","hasCoordinates":false,"isOfficialNetworkNode":false,"isE2EHub":false,"hubCandidate":false,"isDuplicate":false},{"id":"city:vis:belgium:2784548","name":"Vis\u00e9","normalizedName":"vis","country":"Belgium","normalizedCountry":"belgium","subcountry":"Wallonia","geonameid":"2784548","cityStatus":"index_only","hasCoordinates":false,"isOfficialNetworkNode":false,"isE2EHub":false,"hubCandidate":false,"isDuplicate":false},{"id":"city:vilvoorde:belgium:2784604","name":"Vilvoorde","normalizedName":"vilvoorde","country":"Belgium","normalizedCountry":"belgium","subcountry":"Flanders","geonameid":"2784604","cityStatus":"index_only","hasCoordinates":false,"isOfficialNetworkNode":false,"isE2EHub":false,"hubCandidate":false,"isDuplicate":false},{"id":"city:verviers:belgium:2784821","name":"Verviers","normalizedName":"verviers","country":"Belgium","normalizedCountry":"belgium","subcountry":"Wallonia","geonameid":"2784821","cityStatus":"index_only","hasCoordinates":false,"isOfficialNetworkNode":false,"isE2EHub":false,"hubCandidate":false,"isDuplicate":false},{"id":"city:uccle:belgium:2785123","name":"Uccle","normalizedName":"uccle","country":"Belgium","normalizedCountry":"belgium","subcountry":"Brussels Capital","geonameid":"2785123","cityStatus":"index_only","hasCoordinates":false,"isOfficialNetworkNode":false,"isE2EHub":false,"hubCandidate":false,"isDuplicate":false},{"id":"city:turnhout:belgium:2785141","name":"Turnhout","normalizedName":"turnhout","country":"Belgium","normalizedCountry":"belgium","subcountry":"Flanders","geonameid":"2785141","cityStatus":"index_only","hasCoordinates":false,"isOfficialNetworkNode":false,"isE2EHub":false,"hubCandidate":false,"isDuplicate":false},{"id":"city:tubize:belgium:2785169","name":"Tubize","normalizedName":"tubize","country":"Belgium","normalizedCountry":"belgium","subcountry":"Wallonia","geonameid":"2785169","cityStatus":"index_only","hasCoordinates":false,"isOfficialNetworkNode":false,"isE2EHub":false,"hubCandidate":false,"isDuplicate":false},{"id":"city:tournai:belgium:2785341","name":"Tournai","normalizedName":"tournai","country":"Belgium","normalizedCountry":"belgium","subcountry":"Wallonia","geonameid":"2785341","cityStatus":"index_only","hasCoordinates":false,"isOfficialNetworkNode":false,"isE2EHub":false,"hubCandidate":false,"isDuplicate":false},{"id":"city:torhout:belgium:2785364","name":"Torhout","normalizedName":"torhout","country":"Belgium","normalizedCountry":"belgium","subcountry":"Flanders","geonameid":"2785364","cityStatus":"index_only","hasCoordinates":false,"isOfficialNetworkNode":false,"isE2EHub":false,"hubCandidate":false,"isDuplicate":false},{"id":"city:tongeren:belgium:2785389","name":"Tongeren","normalizedName":"tongeren","country":"Belgium","normalizedCountry":"belgium","subcountry":"Flanders","geonameid":"2785389","cityStatus":"index_only","hasCoordinates":false,"isOfficialNetworkNode":false,"isE2EHub":false,"hubCandidate":false,"isDuplicate":false},{"id":"city:tienen:belgium:2785470","name":"Tienen","normalizedName":"tienen","country":"Belgium","normalizedCountry":"belgium","subcountry":"Flanders","geonameid":"2785470","cityStatus":"index_only","hasCoordinates":false,"isOfficialNetworkNode":false,"isE2EHub":false,"hubCandidate":false,"isDuplicate":false},{"id":"city:tielt:belgium:2785476","name":"Tielt","normalizedName":"tielt","country":"Belgium","normalizedCountry":"belgium","subcountry":"Flanders","geonameid":"2785476","cityStatus":"index_only","hasCoordinates":false,"isOfficialNetworkNode":false,"isE2EHub":false,"hubCandidate":false,"isDuplicate":false},{"id":"city:tessenderlo:belgium:2785612","name":"Tessenderlo","normalizedName":"tessenderlo","country":"Belgium","normalizedCountry":"belgium","subcountry":"Flanders","geonameid":"2785612","cityStatus":"index_only","hasCoordinates":false,"isOfficialNetworkNode":false,"isE2EHub":false,"hubCandidate":false,"isDuplicate":false},{"id":"city:tervuren:belgium:2785622","name":"Tervuren","normalizedName":"tervuren","country":"Belgium","normalizedCountry":"belgium","subcountry":"Flanders","geonameid":"2785622","cityStatus":"index_only","hasCoordinates":false,"isOfficialNetworkNode":false,"isE2EHub":false,"hubCandidate":false,"isDuplicate":false},{"id":"city:temse:belgium:2785778","name":"Temse","normalizedName":"temse","country":"Belgium","normalizedCountry":"belgium","subcountry":"Flanders","geonameid":"2785778","cityStatus":"index_only","hasCoordinates":false,"isOfficialNetworkNode":false,"isE2EHub":false,"hubCandidate":false,"isDuplicate":false},{"id":"city:stekene:belgium:2786087","name":"Stekene","normalizedName":"stekene","country":"Belgium","normalizedCountry":"belgium","subcountry":"Flanders","geonameid":"2786087","cityStatus":"index_only","hasCoordinates":false,"isOfficialNetworkNode":false,"isE2EHub":false,"hubCandidate":false,"isDuplicate":false},{"id":"city:stabroek:belgium:2786229","name":"Stabroek","normalizedName":"stabroek","country":"Belgium","normalizedCountry":"belgium","subcountry":"Flanders","geonameid":"2786229","cityStatus":"index_only","hasCoordinates":false,"isOfficialNetworkNode":false,"isE2EHub":false,"hubCandidate":false,"isDuplicate":false},{"id":"city:soumagne:belgium:2786344","name":"Soumagne","normalizedName":"soumagne","country":"Belgium","normalizedCountry":"belgium","subcountry":"Wallonia","geonameid":"2786344","cityStatus":"index_only","hasCoordinates":false,"isOfficialNetworkNode":false,"isE2EHub":false,"hubCandidate":false,"isDuplicate":false},{"id":"city:soignies:belgium:2786420","name":"Soignies","normalizedName":"soignies","country":"Belgium","normalizedCountry":"belgium","subcountry":"Wallonia","geonameid":"2786420","cityStatus":"index_only","hasCoordinates":false,"isOfficialNetworkNode":false,"isE2EHub":false,"hubCandidate":false,"isDuplicate":false},{"id":"city:sint-truiden:belgium:2786545","name":"Sint-Truiden","normalizedName":"sint-truiden","country":"Belgium","normalizedCountry":"belgium","subcountry":"Flanders","geonameid":"2786545","cityStatus":"index_only","hasCoordinates":false,"isOfficialNetworkNode":false,"isE2EHub":false,"hubCandidate":false,"isDuplicate":false},{"id":"city:sint-pieters-leeuw:belgium:2786559","name":"Sint-Pieters-Leeuw","normalizedName":"sint-pieters-leeuw","country":"Belgium","normalizedCountry":"belgium","subcountry":"Flanders","geonameid":"2786559","cityStatus":"index_only","hasCoordinates":false,"isOfficialNetworkNode":false,"isE2EHub":false,"hubCandidate":false,"isDuplicate":false},{"id":"city:sint-niklaas:belgium:2786578","name":"Sint-Niklaas","normalizedName":"sint-niklaas","country":"Belgium","normalizedCountry":"belgium","subcountry":"Flanders","geonameid":"2786578","cityStatus":"index_only","hasCoordinates":false,"isOfficialNetworkNode":false,"isE2EHub":false,"hubCandidate":false,"isDuplicate":false},{"id":"city:sint-kruis:belgium:2786634","name":"Sint-Kruis","normalizedName":"sint-kruis","country":"Belgium","normalizedCountry":"belgium","subcountry":"Flanders","geonameid":"2786634","cityStatus":"index_only","hasCoordinates":false,"isOfficialNetworkNode":false,"isE2EHub":false,"hubCandidate":false,"isDuplicate":false},{"id":"city:sint-katelijne-waver:belgium:2786641","name":"Sint-Katelijne-Waver","normalizedName":"sint-katelijne-waver","country":"Belgium","normalizedCountry":"belgium","subcountry":"Flanders","geonameid":"2786641","cityStatus":"index_only","hasCoordinates":false,"isOfficialNetworkNode":false,"isE2EHub":false,"hubCandidate":false,"isDuplicate":false},{"id":"city:sint-gillis-waas:belgium:2786694","name":"Sint-Gillis-Waas","normalizedName":"sint-gillis-waas","country":"Belgium","normalizedCountry":"belgium","subcountry":"Flanders","geonameid":"2786694","cityStatus":"index_only","hasCoordinates":false,"isOfficialNetworkNode":false,"isE2EHub":false,"hubCandidate":false,"isDuplicate":false},{"id":"city:sint-genesius-rode:belgium:2786700","name":"Sint-Genesius-Rode","normalizedName":"sint-genesius-rode","country":"Belgium","normalizedCountry":"belgium","subcountry":"Flanders","geonameid":"2786700","cityStatus":"index_only","hasCoordinates":false,"isOfficialNetworkNode":false,"isE2EHub":false,"hubCandidate":false,"isDuplicate":false},{"id":"city:sint-andries:belgium:2786739","name":"Sint-Andries","normalizedName":"sint-andries","country":"Belgium","normalizedCountry":"belgium","subcountry":"Flanders","geonameid":"2786739","cityStatus":"index_only","hasCoordinates":false,"isOfficialNetworkNode":false,"isE2EHub":false,"hubCandidate":false,"isDuplicate":false},{"id":"city:sint-amandsberg:belgium:2786743","name":"Sint-Amandsberg","normalizedName":"sint-amandsberg","country":"Belgium","normalizedCountry":"belgium","subcountry":"Flanders","geonameid":"2786743","cityStatus":"index_only","hasCoordinates":false,"isOfficialNetworkNode":false,"isE2EHub":false,"hubCandidate":false,"isDuplicate":false},{"id":"city:seraing:belgium:2786824","name":"Seraing","normalizedName":"seraing","country":"Belgium","normalizedCountry":"belgium","subcountry":"Wallonia","geonameid":"2786824","cityStatus":"index_only","hasCoordinates":false,"isOfficialNetworkNode":false,"isE2EHub":false,"hubCandidate":false,"isDuplicate":false},{"id":"city:schoten:belgium:2786963","name":"Schoten","normalizedName":"schoten","country":"Belgium","normalizedCountry":"belgium","subcountry":"Flanders","geonameid":"2786963","cityStatus":"index_only","hasCoordinates":false,"isOfficialNetworkNode":false,"isE2EHub":false,"hubCandidate":false,"isDuplicate":false},{"id":"city:schilde:belgium:2787048","name":"Schilde","normalizedName":"schilde","country":"Belgium","normalizedCountry":"belgium","subcountry":"Flanders","geonameid":"2787048","cityStatus":"index_only","hasCoordinates":false,"isOfficialNetworkNode":false,"isE2EHub":false,"hubCandidate":false,"isDuplicate":false},{"id":"city:schaerbeek:belgium:2787149","name":"Schaerbeek","normalizedName":"schaerbeek","country":"Belgium","normalizedCountry":"belgium","subcountry":"Brussels Capital","geonameid":"2787149","cityStatus":"index_only","hasCoordinates":false,"isOfficialNetworkNode":false,"isE2EHub":false,"hubCandidate":false,"isDuplicate":false},{"id":"city:saint-nicolas:belgium:2787356","name":"Saint-Nicolas","normalizedName":"saint-nicolas","country":"Belgium","normalizedCountry":"belgium","subcountry":"Wallonia","geonameid":"2787356","cityStatus":"index_only","hasCoordinates":false,"isOfficialNetworkNode":false,"isE2EHub":false,"hubCandidate":false,"isDuplicate":false},{"id":"city:saint-josse-ten-noode:belgium:2787387","name":"Saint-Josse-ten-Noode","normalizedName":"saint-josse-ten-noode","country":"Belgium","normalizedCountry":"belgium","subcountry":"Brussels Capital","geonameid":"2787387","cityStatus":"index_only","hasCoordinates":false,"isOfficialNetworkNode":false,"isE2EHub":false,"hubCandidate":false,"isDuplicate":false},{"id":"city:saint-gilles:belgium:2787413","name":"Saint-Gilles","normalizedName":"saint-gilles","country":"Belgium","normalizedCountry":"belgium","subcountry":"Brussels Capital","geonameid":"2787413","cityStatus":"index_only","hasCoordinates":false,"isOfficialNetworkNode":false,"isE2EHub":false,"hubCandidate":false,"isDuplicate":false},{"id":"city:saint-ghislain:belgium:2787416","name":"Saint-Ghislain","normalizedName":"saint-ghislain","country":"Belgium","normalizedCountry":"belgium","subcountry":"Wallonia","geonameid":"2787416","cityStatus":"index_only","hasCoordinates":false,"isOfficialNetworkNode":false,"isE2EHub":false,"hubCandidate":false,"isDuplicate":false},{"id":"city:rotselaar:belgium:2787662","name":"Rotselaar","normalizedName":"rotselaar","country":"Belgium","normalizedCountry":"belgium","subcountry":"Flanders","geonameid":"2787662","cityStatus":"index_only","hasCoordinates":false,"isOfficialNetworkNode":false,"isE2EHub":false,"hubCandidate":false,"isDuplicate":false},{"id":"city:ronse:belgium:2787769","name":"Ronse","normalizedName":"ronse","country":"Belgium","normalizedCountry":"belgium","subcountry":"Flanders","geonameid":"2787769","cityStatus":"index_only","hasCoordinates":false,"isOfficialNetworkNode":false,"isE2EHub":false,"hubCandidate":false,"isDuplicate":false},{"id":"city:roeselare:belgium:2787889","name":"Roeselare","normalizedName":"roeselare","country":"Belgium","normalizedCountry":"belgium","subcountry":"Flanders","geonameid":"2787889","cityStatus":"index_only","hasCoordinates":false,"isOfficialNetworkNode":false,"isE2EHub":false,"hubCandidate":false,"isDuplicate":false},{"id":"city:rixensart:belgium:2787989","name":"Rixensart","normalizedName":"rixensart","country":"Belgium","normalizedCountry":"belgium","subcountry":"Wallonia","geonameid":"2787989","cityStatus":"index_only","hasCoordinates":false,"isOfficialNetworkNode":false,"isE2EHub":false,"hubCandidate":false,"isDuplicate":false},{"id":"city:riemst:belgium:2788088","name":"Riemst","normalizedName":"riemst","country":"Belgium","normalizedCountry":"belgium","subcountry":"Flanders","geonameid":"2788088","cityStatus":"index_only","hasCoordinates":false,"isOfficialNetworkNode":false,"isE2EHub":false,"hubCandidate":false,"isDuplicate":false},{"id":"city:ranst:belgium:2788348","name":"Ranst","normalizedName":"ranst","country":"Belgium","normalizedCountry":"belgium","subcountry":"Flanders","geonameid":"2788348","cityStatus":"index_only","hasCoordinates":false,"isOfficialNetworkNode":false,"isE2EHub":false,"hubCandidate":false,"isDuplicate":false},{"id":"city:quaregnon:belgium:2788499","name":"Quaregnon","normalizedName":"quaregnon","country":"Belgium","normalizedCountry":"belgium","subcountry":"Wallonia","geonameid":"2788499","cityStatus":"index_only","hasCoordinates":false,"isOfficialNetworkNode":false,"isE2EHub":false,"hubCandidate":false,"isDuplicate":false},{"id":"city:puurs:belgium:2788506","name":"Puurs","normalizedName":"puurs","country":"Belgium","normalizedCountry":"belgium","subcountry":"Flanders","geonameid":"2788506","cityStatus":"index_only","hasCoordinates":false,"isOfficialNetworkNode":false,"isE2EHub":false,"hubCandidate":false,"isDuplicate":false},{"id":"city:putte:belgium:2788521","name":"Putte","normalizedName":"putte","country":"Belgium","normalizedCountry":"belgium","subcountry":"Flanders","geonameid":"2788521","cityStatus":"index_only","hasCoordinates":false,"isOfficialNetworkNode":false,"isE2EHub":false,"hubCandidate":false,"isDuplicate":false},{"id":"city:poperinge:belgium:2788726","name":"Poperinge","normalizedName":"poperinge","country":"Belgium","normalizedCountry":"belgium","subcountry":"Flanders","geonameid":"2788726","cityStatus":"index_only","hasCoordinates":false,"isOfficialNetworkNode":false,"isE2EHub":false,"hubCandidate":false,"isDuplicate":false},{"id":"city:pont-celles:belgium:2788765","name":"Pont-\u00e0-Celles","normalizedName":"pont-celles","country":"Belgium","normalizedCountry":"belgium","subcountry":"Wallonia","geonameid":"2788765","cityStatus":"index_only","hasCoordinates":false,"isOfficialNetworkNode":false,"isE2EHub":false,"hubCandidate":false,"isDuplicate":false},{"id":"city:p-ruwelz:belgium:2789162","name":"P\u00e9ruwelz","normalizedName":"p-ruwelz","country":"Belgium","normalizedCountry":"belgium","subcountry":"Wallonia","geonameid":"2789162","cityStatus":"index_only","hasCoordinates":false,"isOfficialNetworkNode":false,"isE2EHub":false,"hubCandidate":false,"isDuplicate":false},{"id":"city:peer:belgium:2789232","name":"Peer","normalizedName":"peer","country":"Belgium","normalizedCountry":"belgium","subcountry":"Flanders","geonameid":"2789232","cityStatus":"index_only","hasCoordinates":false,"isOfficialNetworkNode":false,"isE2EHub":false,"hubCandidate":false,"isDuplicate":false},{"id":"city:overijse:belgium:2789413","name":"Overijse","normalizedName":"overijse","country":"Belgium","normalizedCountry":"belgium","subcountry":"Flanders","geonameid":"2789413","cityStatus":"index_only","hasCoordinates":false,"isOfficialNetworkNode":false,"isE2EHub":false,"hubCandidate":false,"isDuplicate":false},{"id":"city:oupeye:belgium:2789471","name":"Oupeye","normalizedName":"oupeye","country":"Belgium","normalizedCountry":"belgium","subcountry":"Wallonia","geonameid":"2789471","cityStatus":"index_only","hasCoordinates":false,"isOfficialNetworkNode":false,"isE2EHub":false,"hubCandidate":false,"isDuplicate":false},{"id":"city:oudenaarde:belgium:2789529","name":"Oudenaarde","normalizedName":"oudenaarde","country":"Belgium","normalizedCountry":"belgium","subcountry":"Flanders","geonameid":"2789529","cityStatus":"index_only","hasCoordinates":false,"isOfficialNetworkNode":false,"isE2EHub":false,"hubCandidate":false,"isDuplicate":false},{"id":"city:oostkamp:belgium:2789751","name":"Oostkamp","normalizedName":"oostkamp","country":"Belgium","normalizedCountry":"belgium","subcountry":"Flanders","geonameid":"2789751","cityStatus":"index_only","hasCoordinates":false,"isOfficialNetworkNode":false,"isE2EHub":false,"hubCandidate":false,"isDuplicate":false},{"id":"city:ostend:belgium:2789786","name":"Ostend","normalizedName":"ostend","country":"Belgium","normalizedCountry":"belgium","subcountry":"Flanders","geonameid":"2789786","cityStatus":"index_only","hasCoordinates":false,"isOfficialNetworkNode":false,"isE2EHub":false,"hubCandidate":false,"isDuplicate":false},{"id":"city:nivelles:belgium:2790101","name":"Nivelles","normalizedName":"nivelles","country":"Belgium","normalizedCountry":"belgium","subcountry":"Wallonia","geonameid":"2790101","cityStatus":"index_only","hasCoordinates":false,"isOfficialNetworkNode":false,"isE2EHub":false,"hubCandidate":false,"isDuplicate":false},{"id":"city:ninove:belgium:2790114","name":"Ninove","normalizedName":"ninove","country":"Belgium","normalizedCountry":"belgium","subcountry":"Flanders","geonameid":"2790114","cityStatus":"index_only","hasCoordinates":false,"isOfficialNetworkNode":false,"isE2EHub":false,"hubCandidate":false,"isDuplicate":false},{"id":"city:nijlen:belgium:2790135","name":"Nijlen","normalizedName":"nijlen","country":"Belgium","normalizedCountry":"belgium","subcountry":"Flanders","geonameid":"2790135","cityStatus":"index_only","hasCoordinates":false,"isOfficialNetworkNode":false,"isE2EHub":false,"hubCandidate":false,"isDuplicate":false},{"id":"city:neerpelt:belgium:2790357","name":"Neerpelt","normalizedName":"neerpelt","country":"Belgium","normalizedCountry":"belgium","subcountry":"Flanders","geonameid":"2790357","cityStatus":"index_only","hasCoordinates":false,"isOfficialNetworkNode":false,"isE2EHub":false,"hubCandidate":false,"isDuplicate":false},{"id":"city:namur:belgium:2790471","name":"Namur","normalizedName":"namur","country":"Belgium","normalizedCountry":"belgium","subcountry":"Wallonia","geonameid":"2790471","cityStatus":"index_only","hasCoordinates":false,"isOfficialNetworkNode":false,"isE2EHub":false,"hubCandidate":false,"isDuplicate":false},{"id":"city:mouscron:belgium:2790595","name":"Mouscron","normalizedName":"mouscron","country":"Belgium","normalizedCountry":"belgium","subcountry":"Wallonia","geonameid":"2790595","cityStatus":"index_only","hasCoordinates":false,"isOfficialNetworkNode":false,"isE2EHub":false,"hubCandidate":false,"isDuplicate":false},{"id":"city:mortsel:belgium:2790676","name":"Mortsel","normalizedName":"mortsel","country":"Belgium","normalizedCountry":"belgium","subcountry":"Flanders","geonameid":"2790676","cityStatus":"index_only","hasCoordinates":false,"isOfficialNetworkNode":false,"isE2EHub":false,"hubCandidate":false,"isDuplicate":false},{"id":"city:morlanwelz-mariemont:belgium:2790697","name":"Morlanwelz-Mariemont","normalizedName":"morlanwelz-mariemont","country":"Belgium","normalizedCountry":"belgium","subcountry":"Wallonia","geonameid":"2790697","cityStatus":"index_only","hasCoordinates":false,"isOfficialNetworkNode":false,"isE2EHub":false,"hubCandidate":false,"isDuplicate":false},{"id":"city:montignies-sur-sambre:belgium:2790796","name":"Montignies-sur-Sambre","normalizedName":"montignies-sur-sambre","country":"Belgium","normalizedCountry":"belgium","subcountry":"Wallonia","geonameid":"2790796","cityStatus":"index_only","hasCoordinates":false,"isOfficialNetworkNode":false,"isE2EHub":false,"hubCandidate":false,"isDuplicate":false},{"id":"city:mons:belgium:2790869","name":"Mons","normalizedName":"mons","country":"Belgium","normalizedCountry":"belgium","subcountry":"Wallonia","geonameid":"2790869","cityStatus":"index_only","hasCoordinates":false,"isOfficialNetworkNode":false,"isE2EHub":false,"hubCandidate":false,"isDuplicate":false},{"id":"city:molenbeek-saint-jean:belgium:2791018","name":"Molenbeek-Saint-Jean","normalizedName":"molenbeek-saint-jean","country":"Belgium","normalizedCountry":"belgium","subcountry":"Brussels Capital","geonameid":"2791018","cityStatus":"index_only","hasCoordinates":false,"isOfficialNetworkNode":false,"isE2EHub":false,"hubCandidate":false,"isDuplicate":false},{"id":"city:mol:belgium:2791067","name":"Mol","normalizedName":"mol","country":"Belgium","normalizedCountry":"belgium","subcountry":"Flanders","geonameid":"2791067","cityStatus":"index_only","hasCoordinates":false,"isOfficialNetworkNode":false,"isE2EHub":false,"hubCandidate":false,"isDuplicate":false},{"id":"city:middelkerke:belgium:2791194","name":"Middelkerke","normalizedName":"middelkerke","country":"Belgium","normalizedCountry":"belgium","subcountry":"Flanders","geonameid":"2791194","cityStatus":"index_only","hasCoordinates":false,"isOfficialNetworkNode":false,"isE2EHub":false,"hubCandidate":false,"isDuplicate":false},{"id":"city:merksem:belgium:2791301","name":"Merksem","normalizedName":"merksem","country":"Belgium","normalizedCountry":"belgium","subcountry":"Flanders","geonameid":"2791301","cityStatus":"index_only","hasCoordinates":false,"isOfficialNetworkNode":false,"isE2EHub":false,"hubCandidate":false,"isDuplicate":false},{"id":"city:merelbeke:belgium:2791315","name":"Merelbeke","normalizedName":"merelbeke","country":"Belgium","normalizedCountry":"belgium","subcountry":"Flanders","geonameid":"2791315","cityStatus":"index_only","hasCoordinates":false,"isOfficialNetworkNode":false,"isE2EHub":false,"hubCandidate":false,"isDuplicate":false},{"id":"city:menen:belgium:2791343","name":"Menen","normalizedName":"menen","country":"Belgium","normalizedCountry":"belgium","subcountry":"Flanders","geonameid":"2791343","cityStatus":"index_only","hasCoordinates":false,"isOfficialNetworkNode":false,"isE2EHub":false,"hubCandidate":false,"isDuplicate":false},{"id":"city:meise:belgium:2791424","name":"Meise","normalizedName":"meise","country":"Belgium","normalizedCountry":"belgium","subcountry":"Flanders","geonameid":"2791424","cityStatus":"index_only","hasCoordinates":false,"isOfficialNetworkNode":false,"isE2EHub":false,"hubCandidate":false,"isDuplicate":false},{"id":"city:mechelen-aan-de-maas:belgium:2791534","name":"Mechelen-aan-de-Maas","normalizedName":"mechelen-aan-de-maas","country":"Belgium","normalizedCountry":"belgium","subcountry":"Flanders","geonameid":"2791534","cityStatus":"index_only","hasCoordinates":false,"isOfficialNetworkNode":false,"isE2EHub":false,"hubCandidate":false,"isDuplicate":false},{"id":"city:mechelen:belgium:2791537","name":"Mechelen","normalizedName":"mechelen","country":"Belgium","normalizedCountry":"belgium","subcountry":"Flanders","geonameid":"2791537","cityStatus":"index_only","hasCoordinates":false,"isOfficialNetworkNode":false,"isE2EHub":false,"hubCandidate":false,"isDuplicate":false},{"id":"city:mariakerke:belgium:2791700","name":"Mariakerke","normalizedName":"mariakerke","country":"Belgium","normalizedCountry":"belgium","subcountry":"Flanders","geonameid":"2791700","cityStatus":"index_only","hasCoordinates":false,"isOfficialNetworkNode":false,"isE2EHub":false,"hubCandidate":false,"isDuplicate":false},{"id":"city:marcinelle:belgium:2791726","name":"Marcinelle","normalizedName":"marcinelle","country":"Belgium","normalizedCountry":"belgium","subcountry":"Wallonia","geonameid":"2791726","cityStatus":"index_only","hasCoordinates":false,"isOfficialNetworkNode":false,"isE2EHub":false,"hubCandidate":false,"isDuplicate":false},{"id":"city:marchienne-au-pont:belgium:2791735","name":"Marchienne-au-Pont","normalizedName":"marchienne-au-pont","country":"Belgium","normalizedCountry":"belgium","subcountry":"Wallonia","geonameid":"2791735","cityStatus":"index_only","hasCoordinates":false,"isOfficialNetworkNode":false,"isE2EHub":false,"hubCandidate":false,"isDuplicate":false},{"id":"city:marche-en-famenne:belgium:2791744","name":"Marche-en-Famenne","normalizedName":"marche-en-famenne","country":"Belgium","normalizedCountry":"belgium","subcountry":"Wallonia","geonameid":"2791744","cityStatus":"index_only","hasCoordinates":false,"isOfficialNetworkNode":false,"isE2EHub":false,"hubCandidate":false,"isDuplicate":false},{"id":"city:manage:belgium:2791814","name":"Manage","normalizedName":"manage","country":"Belgium","normalizedCountry":"belgium","subcountry":"Wallonia","geonameid":"2791814","cityStatus":"index_only","hasCoordinates":false,"isOfficialNetworkNode":false,"isE2EHub":false,"hubCandidate":false,"isDuplicate":false},{"id":"city:maldegem:belgium:2791857","name":"Maldegem","normalizedName":"maldegem","country":"Belgium","normalizedCountry":"belgium","subcountry":"Flanders","geonameid":"2791857","cityStatus":"index_only","hasCoordinates":false,"isOfficialNetworkNode":false,"isE2EHub":false,"hubCandidate":false,"isDuplicate":false},{"id":"city:maasmechelen:belgium:2791961","name":"Maasmechelen","normalizedName":"maasmechelen","country":"Belgium","normalizedCountry":"belgium","subcountry":"Flanders","geonameid":"2791961","cityStatus":"index_only","hasCoordinates":false,"isOfficialNetworkNode":false,"isE2EHub":false,"hubCandidate":false,"isDuplicate":false},{"id":"city:maaseik:belgium:2791964","name":"Maaseik","normalizedName":"maaseik","country":"Belgium","normalizedCountry":"belgium","subcountry":"Flanders","geonameid":"2791964","cityStatus":"index_only","hasCoordinates":false,"isOfficialNetworkNode":false,"isE2EHub":false,"hubCandidate":false,"isDuplicate":false},{"id":"city:louvain-la-neuve:belgium:2792073","name":"Louvain-la-Neuve","normalizedName":"louvain-la-neuve","country":"Belgium","normalizedCountry":"belgium","subcountry":"Wallonia","geonameid":"2792073","cityStatus":"index_only","hasCoordinates":false,"isOfficialNetworkNode":false,"isE2EHub":false,"hubCandidate":false,"isDuplicate":false},{"id":"city:lommel:belgium:2792179","name":"Lommel","normalizedName":"lommel","country":"Belgium","normalizedCountry":"belgium","subcountry":"Flanders","geonameid":"2792179","cityStatus":"index_only","hasCoordinates":false,"isOfficialNetworkNode":false,"isE2EHub":false,"hubCandidate":false,"isDuplicate":false},{"id":"city:lokeren:belgium:2792196","name":"Lokeren","normalizedName":"lokeren","country":"Belgium","normalizedCountry":"belgium","subcountry":"Flanders","geonameid":"2792196","cityStatus":"index_only","hasCoordinates":false,"isOfficialNetworkNode":false,"isE2EHub":false,"hubCandidate":false,"isDuplicate":false},{"id":"city:lochristi:belgium:2792235","name":"Lochristi","normalizedName":"lochristi","country":"Belgium","normalizedCountry":"belgium","subcountry":"Flanders","geonameid":"2792235","cityStatus":"index_only","hasCoordinates":false,"isOfficialNetworkNode":false,"isE2EHub":false,"hubCandidate":false,"isDuplicate":false},{"id":"city:lille:belgium:2792360","name":"Lille","normalizedName":"lille","country":"Belgium","normalizedCountry":"belgium","subcountry":"Flanders","geonameid":"2792360","cityStatus":"index_only","hasCoordinates":false,"isOfficialNetworkNode":false,"isE2EHub":false,"hubCandidate":false,"isDuplicate":false},{"id":"city:lier:belgium:2792397","name":"Lier","normalizedName":"lier","country":"Belgium","normalizedCountry":"belgium","subcountry":"Flanders","geonameid":"2792397","cityStatus":"index_only","hasCoordinates":false,"isOfficialNetworkNode":false,"isE2EHub":false,"hubCandidate":false,"isDuplicate":false},{"id":"city:li-ge:belgium:2792413","name":"Li\u00e8ge","normalizedName":"li-ge","country":"Belgium","normalizedCountry":"belgium","subcountry":"Wallonia","geonameid":"2792413","cityStatus":"index_only","hasCoordinates":false,"isOfficialNetworkNode":false,"isE2EHub":false,"hubCandidate":false,"isDuplicate":false},{"id":"city:leuven:belgium:2792482","name":"Leuven","normalizedName":"leuven","country":"Belgium","normalizedCountry":"belgium","subcountry":"Flanders","geonameid":"2792482","cityStatus":"index_only","hasCoordinates":false,"isOfficialNetworkNode":false,"isE2EHub":false,"hubCandidate":false,"isDuplicate":false},{"id":"city:lessines:belgium:2792567","name":"Lessines","normalizedName":"lessines","country":"Belgium","normalizedCountry":"belgium","subcountry":"Wallonia","geonameid":"2792567","cityStatus":"index_only","hasCoordinates":false,"isOfficialNetworkNode":false,"isE2EHub":false,"hubCandidate":false,"isDuplicate":false},{"id":"city:lede:belgium:2793077","name":"Lede","normalizedName":"lede","country":"Belgium","normalizedCountry":"belgium","subcountry":"Flanders","geonameid":"2793077","cityStatus":"index_only","hasCoordinates":false,"isOfficialNetworkNode":false,"isE2EHub":false,"hubCandidate":false,"isDuplicate":false},{"id":"city:lebbeke:belgium:2793144","name":"Lebbeke","normalizedName":"lebbeke","country":"Belgium","normalizedCountry":"belgium","subcountry":"Flanders","geonameid":"2793144","cityStatus":"index_only","hasCoordinates":false,"isOfficialNetworkNode":false,"isE2EHub":false,"hubCandidate":false,"isDuplicate":false},{"id":"city:lanaken:belgium:2793446","name":"Lanaken","normalizedName":"lanaken","country":"Belgium","normalizedCountry":"belgium","subcountry":"Flanders","geonameid":"2793446","cityStatus":"index_only","hasCoordinates":false,"isOfficialNetworkNode":false,"isE2EHub":false,"hubCandidate":false,"isDuplicate":false},{"id":"city:la-louvi-re:belgium:2793508","name":"La Louvi\u00e8re","normalizedName":"la-louvi-re","country":"Belgium","normalizedCountry":"belgium","subcountry":"Wallonia","geonameid":"2793508","cityStatus":"index_only","hasCoordinates":false,"isOfficialNetworkNode":false,"isE2EHub":false,"hubCandidate":false,"isDuplicate":false},{"id":"city:kortrijk:belgium:2794055","name":"Kortrijk","normalizedName":"kortrijk","country":"Belgium","normalizedCountry":"belgium","subcountry":"Flanders","geonameid":"2794055","cityStatus":"index_only","hasCoordinates":false,"isOfficialNetworkNode":false,"isE2EHub":false,"hubCandidate":false,"isDuplicate":false},{"id":"city:kortenberg:belgium:2794070","name":"Kortenberg","normalizedName":"kortenberg","country":"Belgium","normalizedCountry":"belgium","subcountry":"Flanders","geonameid":"2794070","cityStatus":"index_only","hasCoordinates":false,"isOfficialNetworkNode":false,"isE2EHub":false,"hubCandidate":false,"isDuplicate":false},{"id":"city:kontich:belgium:2794117","name":"Kontich","normalizedName":"kontich","country":"Belgium","normalizedCountry":"belgium","subcountry":"Flanders","geonameid":"2794117","cityStatus":"index_only","hasCoordinates":false,"isOfficialNetworkNode":false,"isE2EHub":false,"hubCandidate":false,"isDuplicate":false},{"id":"city:koksijde:belgium:2794166","name":"Koksijde","normalizedName":"koksijde","country":"Belgium","normalizedCountry":"belgium","subcountry":"Flanders","geonameid":"2794166","cityStatus":"index_only","hasCoordinates":false,"isOfficialNetworkNode":false,"isE2EHub":false,"hubCandidate":false,"isDuplicate":false},{"id":"city:koersel:belgium:2794179","name":"Koersel","normalizedName":"koersel","country":"Belgium","normalizedCountry":"belgium","subcountry":"Flanders","geonameid":"2794179","cityStatus":"index_only","hasCoordinates":false,"isOfficialNetworkNode":false,"isE2EHub":false,"hubCandidate":false,"isDuplicate":false},{"id":"city:koekelberg:belgium:2794190","name":"Koekelberg","normalizedName":"koekelberg","country":"Belgium","normalizedCountry":"belgium","subcountry":"Brussels Capital","geonameid":"2794190","cityStatus":"index_only","hasCoordinates":false,"isOfficialNetworkNode":false,"isE2EHub":false,"hubCandidate":false,"isDuplicate":false},{"id":"city:knokke-heist:belgium:2794210","name":"Knokke-Heist","normalizedName":"knokke-heist","country":"Belgium","normalizedCountry":"belgium","subcountry":"Flanders","geonameid":"2794210","cityStatus":"index_only","hasCoordinates":false,"isOfficialNetworkNode":false,"isE2EHub":false,"hubCandidate":false,"isDuplicate":false},{"id":"city:kessel-lo:belgium:2794507","name":"Kessel-Lo","normalizedName":"kessel-lo","country":"Belgium","normalizedCountry":"belgium","subcountry":"Flanders","geonameid":"2794507","cityStatus":"index_only","hasCoordinates":false,"isOfficialNetworkNode":false,"isE2EHub":false,"hubCandidate":false,"isDuplicate":false},{"id":"city:kasterlee:belgium:2794663","name":"Kasterlee","normalizedName":"kasterlee","country":"Belgium","normalizedCountry":"belgium","subcountry":"Flanders","geonameid":"2794663","cityStatus":"index_only","hasCoordinates":false,"isOfficialNetworkNode":false,"isE2EHub":false,"hubCandidate":false,"isDuplicate":false},{"id":"city:kapellen:belgium:2794730","name":"Kapellen","normalizedName":"kapellen","country":"Belgium","normalizedCountry":"belgium","subcountry":"Flanders","geonameid":"2794730","cityStatus":"index_only","hasCoordinates":false,"isOfficialNetworkNode":false,"isE2EHub":false,"hubCandidate":false,"isDuplicate":false},{"id":"city:kalmthout:belgium:2794788","name":"Kalmthout","normalizedName":"kalmthout","country":"Belgium","normalizedCountry":"belgium","subcountry":"Flanders","geonameid":"2794788","cityStatus":"index_only","hasCoordinates":false,"isOfficialNetworkNode":false,"isE2EHub":false,"hubCandidate":false,"isDuplicate":false},{"id":"city:jumet:belgium:2794860","name":"Jumet","normalizedName":"jumet","country":"Belgium","normalizedCountry":"belgium","subcountry":"Wallonia","geonameid":"2794860","cityStatus":"index_only","hasCoordinates":false,"isOfficialNetworkNode":false,"isE2EHub":false,"hubCandidate":false,"isDuplicate":false},{"id":"city:jette:belgium:2794914","name":"Jette","normalizedName":"jette","country":"Belgium","normalizedCountry":"belgium","subcountry":"Brussels Capital","geonameid":"2794914","cityStatus":"index_only","hasCoordinates":false,"isOfficialNetworkNode":false,"isE2EHub":false,"hubCandidate":false,"isDuplicate":false},{"id":"city:jambes:belgium:2794981","name":"Jambes","normalizedName":"jambes","country":"Belgium","normalizedCountry":"belgium","subcountry":"Wallonia","geonameid":"2794981","cityStatus":"index_only","hasCoordinates":false,"isOfficialNetworkNode":false,"isE2EHub":false,"hubCandidate":false,"isDuplicate":false},{"id":"city:izegem:belgium:2795009","name":"Izegem","normalizedName":"izegem","country":"Belgium","normalizedCountry":"belgium","subcountry":"Flanders","geonameid":"2795009","cityStatus":"index_only","hasCoordinates":false,"isOfficialNetworkNode":false,"isE2EHub":false,"hubCandidate":false,"isDuplicate":false},{"id":"city:ixelles:belgium:2795011","name":"Ixelles","normalizedName":"ixelles","country":"Belgium","normalizedCountry":"belgium","subcountry":"Brussels Capital","geonameid":"2795011","cityStatus":"index_only","hasCoordinates":false,"isOfficialNetworkNode":false,"isE2EHub":false,"hubCandidate":false,"isDuplicate":false},{"id":"city:ieper:belgium:2795100","name":"Ieper","normalizedName":"ieper","country":"Belgium","normalizedCountry":"belgium","subcountry":"Flanders","geonameid":"2795100","cityStatus":"index_only","hasCoordinates":false,"isOfficialNetworkNode":false,"isE2EHub":false,"hubCandidate":false,"isDuplicate":false},{"id":"city:huy:belgium:2795113","name":"Huy","normalizedName":"huy","country":"Belgium","normalizedCountry":"belgium","subcountry":"Wallonia","geonameid":"2795113","cityStatus":"index_only","hasCoordinates":false,"isOfficialNetworkNode":false,"isE2EHub":false,"hubCandidate":false,"isDuplicate":false},{"id":"city:houthalen:belgium:2795261","name":"Houthalen","normalizedName":"houthalen","country":"Belgium","normalizedCountry":"belgium","subcountry":"Flanders","geonameid":"2795261","cityStatus":"index_only","hasCoordinates":false,"isOfficialNetworkNode":false,"isE2EHub":false,"hubCandidate":false,"isDuplicate":false},{"id":"city:hoogstraten:belgium:2795398","name":"Hoogstraten","normalizedName":"hoogstraten","country":"Belgium","normalizedCountry":"belgium","subcountry":"Flanders","geonameid":"2795398","cityStatus":"index_only","hasCoordinates":false,"isOfficialNetworkNode":false,"isE2EHub":false,"hubCandidate":false,"isDuplicate":false},{"id":"city:hoboken:belgium:2795730","name":"Hoboken","normalizedName":"hoboken","country":"Belgium","normalizedCountry":"belgium","subcountry":"Flanders","geonameid":"2795730","cityStatus":"index_only","hasCoordinates":false,"isOfficialNetworkNode":false,"isE2EHub":false,"hubCandidate":false,"isDuplicate":false},{"id":"city:heverlee:belgium:2795783","name":"Heverlee","normalizedName":"heverlee","country":"Belgium","normalizedCountry":"belgium","subcountry":"Flanders","geonameid":"2795783","cityStatus":"index_only","hasCoordinates":false,"isOfficialNetworkNode":false,"isE2EHub":false,"hubCandidate":false,"isDuplicate":false},{"id":"city:heusy:belgium:2795795","name":"Heusy","normalizedName":"heusy","country":"Belgium","normalizedCountry":"belgium","subcountry":"Wallonia","geonameid":"2795795","cityStatus":"index_only","hasCoordinates":false,"isOfficialNetworkNode":false,"isE2EHub":false,"hubCandidate":false,"isDuplicate":false},{"id":"city:heusden:belgium:2795800","name":"Heusden","normalizedName":"heusden","country":"Belgium","normalizedCountry":"belgium","subcountry":"Flanders","geonameid":"2795800","cityStatus":"index_only","hasCoordinates":false,"isOfficialNetworkNode":false,"isE2EHub":false,"hubCandidate":false,"isDuplicate":false},{"id":"city:herzele:belgium:2795908","name":"Herzele","normalizedName":"herzele","country":"Belgium","normalizedCountry":"belgium","subcountry":"Flanders","geonameid":"2795908","cityStatus":"index_only","hasCoordinates":false,"isOfficialNetworkNode":false,"isE2EHub":false,"hubCandidate":false,"isDuplicate":false},{"id":"city:herve:belgium:2795912","name":"Herve","normalizedName":"herve","country":"Belgium","normalizedCountry":"belgium","subcountry":"Wallonia","geonameid":"2795912","cityStatus":"index_only","hasCoordinates":false,"isOfficialNetworkNode":false,"isE2EHub":false,"hubCandidate":false,"isDuplicate":false},{"id":"city:herstal:belgium:2795930","name":"Herstal","normalizedName":"herstal","country":"Belgium","normalizedCountry":"belgium","subcountry":"Wallonia","geonameid":"2795930","cityStatus":"index_only","hasCoordinates":false,"isOfficialNetworkNode":false,"isE2EHub":false,"hubCandidate":false,"isDuplicate":false},{"id":"city:herentals:belgium:2796009","name":"Herentals","normalizedName":"herentals","country":"Belgium","normalizedCountry":"belgium","subcountry":"Flanders","geonameid":"2796009","cityStatus":"index_only","hasCoordinates":false,"isOfficialNetworkNode":false,"isE2EHub":false,"hubCandidate":false,"isDuplicate":false},{"id":"city:herent:belgium:2796012","name":"Herent","normalizedName":"herent","country":"Belgium","normalizedCountry":"belgium","subcountry":"Flanders","geonameid":"2796012","cityStatus":"index_only","hasCoordinates":false,"isOfficialNetworkNode":false,"isE2EHub":false,"hubCandidate":false,"isDuplicate":false},{"id":"city:helchteren:belgium:2796132","name":"Helchteren","normalizedName":"helchteren","country":"Belgium","normalizedCountry":"belgium","subcountry":"Flanders","geonameid":"2796132","cityStatus":"index_only","hasCoordinates":false,"isOfficialNetworkNode":false,"isE2EHub":false,"hubCandidate":false,"isDuplicate":false},{"id":"city:heist-op-den-berg:belgium:2796153","name":"Heist-op-den-Berg","normalizedName":"heist-op-den-berg","country":"Belgium","normalizedCountry":"belgium","subcountry":"Flanders","geonameid":"2796153","cityStatus":"index_only","hasCoordinates":false,"isOfficialNetworkNode":false,"isE2EHub":false,"hubCandidate":false,"isDuplicate":false},{"id":"city:hasselt:belgium:2796491","name":"Hasselt","normalizedName":"hasselt","country":"Belgium","normalizedCountry":"belgium","subcountry":"Flanders","geonameid":"2796491","cityStatus":"index_only","hasCoordinates":false,"isOfficialNetworkNode":false,"isE2EHub":false,"hubCandidate":false,"isDuplicate":false},{"id":"city:harelbeke:belgium:2796542","name":"Harelbeke","normalizedName":"harelbeke","country":"Belgium","normalizedCountry":"belgium","subcountry":"Flanders","geonameid":"2796542","cityStatus":"index_only","hasCoordinates":false,"isOfficialNetworkNode":false,"isE2EHub":false,"hubCandidate":false,"isDuplicate":false},{"id":"city:hamme:belgium:2796637","name":"Hamme","normalizedName":"hamme","country":"Belgium","normalizedCountry":"belgium","subcountry":"Flanders","geonameid":"2796637","cityStatus":"index_only","hasCoordinates":false,"isOfficialNetworkNode":false,"isE2EHub":false,"hubCandidate":false,"isDuplicate":false},{"id":"city:halle:belgium:2796696","name":"Halle","normalizedName":"halle","country":"Belgium","normalizedCountry":"belgium","subcountry":"Flanders","geonameid":"2796696","cityStatus":"index_only","hasCoordinates":false,"isOfficialNetworkNode":false,"isE2EHub":false,"hubCandidate":false,"isDuplicate":false},{"id":"city:haaltert:belgium:2796833","name":"Haaltert","normalizedName":"haaltert","country":"Belgium","normalizedCountry":"belgium","subcountry":"Flanders","geonameid":"2796833","cityStatus":"index_only","hasCoordinates":false,"isOfficialNetworkNode":false,"isE2EHub":false,"hubCandidate":false,"isDuplicate":false},{"id":"city:grivegn-e:belgium:2797096","name":"Grivegn\u00e9e","normalizedName":"grivegn-e","country":"Belgium","normalizedCountry":"belgium","subcountry":"Wallonia","geonameid":"2797096","cityStatus":"index_only","hasCoordinates":false,"isOfficialNetworkNode":false,"isE2EHub":false,"hubCandidate":false,"isDuplicate":false},{"id":"city:grimbergen:belgium:2797114","name":"Grimbergen","normalizedName":"grimbergen","country":"Belgium","normalizedCountry":"belgium","subcountry":"Flanders","geonameid":"2797114","cityStatus":"index_only","hasCoordinates":false,"isOfficialNetworkNode":false,"isE2EHub":false,"hubCandidate":false,"isDuplicate":false},{"id":"city:gilly:belgium:2797532","name":"Gilly","normalizedName":"gilly","country":"Belgium","normalizedCountry":"belgium","subcountry":"Wallonia","geonameid":"2797532","cityStatus":"index_only","hasCoordinates":false,"isOfficialNetworkNode":false,"isE2EHub":false,"hubCandidate":false,"isDuplicate":false},{"id":"city:geraardsbergen:belgium:2797638","name":"Geraardsbergen","normalizedName":"geraardsbergen","country":"Belgium","normalizedCountry":"belgium","subcountry":"Flanders","geonameid":"2797638","cityStatus":"index_only","hasCoordinates":false,"isOfficialNetworkNode":false,"isE2EHub":false,"hubCandidate":false,"isDuplicate":false},{"id":"city:gentbrugge:belgium:2797652","name":"Gentbrugge","normalizedName":"gentbrugge","country":"Belgium","normalizedCountry":"belgium","subcountry":"Flanders","geonameid":"2797652","cityStatus":"index_only","hasCoordinates":false,"isOfficialNetworkNode":false,"isE2EHub":false,"hubCandidate":false,"isDuplicate":false},{"id":"city:gent:belgium:2797656","name":"Gent","normalizedName":"gent","country":"Belgium","normalizedCountry":"belgium","subcountry":"Flanders","geonameid":"2797656","cityStatus":"index_only","hasCoordinates":false,"isOfficialNetworkNode":false,"isE2EHub":false,"hubCandidate":false,"isDuplicate":false},{"id":"city:genk:belgium:2797670","name":"Genk","normalizedName":"genk","country":"Belgium","normalizedCountry":"belgium","subcountry":"Flanders","geonameid":"2797670","cityStatus":"index_only","hasCoordinates":false,"isOfficialNetworkNode":false,"isE2EHub":false,"hubCandidate":false,"isDuplicate":false},{"id":"city:gembloux:belgium:2797713","name":"Gembloux","normalizedName":"gembloux","country":"Belgium","normalizedCountry":"belgium","subcountry":"Wallonia","geonameid":"2797713","cityStatus":"index_only","hasCoordinates":false,"isOfficialNetworkNode":false,"isE2EHub":false,"hubCandidate":false,"isDuplicate":false},{"id":"city:geel:belgium:2797779","name":"Geel","normalizedName":"geel","country":"Belgium","normalizedCountry":"belgium","subcountry":"Flanders","geonameid":"2797779","cityStatus":"index_only","hasCoordinates":false,"isOfficialNetworkNode":false,"isE2EHub":false,"hubCandidate":false,"isDuplicate":false},{"id":"city:ganshoren:belgium:2797844","name":"Ganshoren","normalizedName":"ganshoren","country":"Belgium","normalizedCountry":"belgium","subcountry":"Brussels Capital","geonameid":"2797844","cityStatus":"index_only","hasCoordinates":false,"isOfficialNetworkNode":false,"isE2EHub":false,"hubCandidate":false,"isDuplicate":false},{"id":"city:frameries:belgium:2798023","name":"Frameries","normalizedName":"frameries","country":"Belgium","normalizedCountry":"belgium","subcountry":"Wallonia","geonameid":"2798023","cityStatus":"index_only","hasCoordinates":false,"isOfficialNetworkNode":false,"isE2EHub":false,"hubCandidate":false,"isDuplicate":false},{"id":"city:forest:belgium:2798139","name":"Forest","normalizedName":"forest","country":"Belgium","normalizedCountry":"belgium","subcountry":"Brussels Capital","geonameid":"2798139","cityStatus":"index_only","hasCoordinates":false,"isOfficialNetworkNode":false,"isE2EHub":false,"hubCandidate":false,"isDuplicate":false},{"id":"city:fleurus:belgium:2798297","name":"Fleurus","normalizedName":"fleurus","country":"Belgium","normalizedCountry":"belgium","subcountry":"Wallonia","geonameid":"2798297","cityStatus":"index_only","hasCoordinates":false,"isOfficialNetworkNode":false,"isE2EHub":false,"hubCandidate":false,"isDuplicate":false},{"id":"city:fl-ron:belgium:2798301","name":"Fl\u00e9ron","normalizedName":"fl-ron","country":"Belgium","normalizedCountry":"belgium","subcountry":"Wallonia","geonameid":"2798301","cityStatus":"index_only","hasCoordinates":false,"isOfficialNetworkNode":false,"isE2EHub":false,"hubCandidate":false,"isDuplicate":false},{"id":"city:fl-malle-haute:belgium:2798307","name":"Fl\u00e9malle-Haute","normalizedName":"fl-malle-haute","country":"Belgium","normalizedCountry":"belgium","subcountry":"Wallonia","geonameid":"2798307","cityStatus":"index_only","hasCoordinates":false,"isOfficialNetworkNode":false,"isE2EHub":false,"hubCandidate":false,"isDuplicate":false},{"id":"city:evergem:belgium:2798551","name":"Evergem","normalizedName":"evergem","country":"Belgium","normalizedCountry":"belgium","subcountry":"Flanders","geonameid":"2798551","cityStatus":"index_only","hasCoordinates":false,"isOfficialNetworkNode":false,"isE2EHub":false,"hubCandidate":false,"isDuplicate":false},{"id":"city:evere:belgium:2798554","name":"Evere","normalizedName":"evere","country":"Belgium","normalizedCountry":"belgium","subcountry":"Brussels Capital","geonameid":"2798554","cityStatus":"index_only","hasCoordinates":false,"isOfficialNetworkNode":false,"isE2EHub":false,"hubCandidate":false,"isDuplicate":false},{"id":"city:eupen:belgium:2798573","name":"Eupen","normalizedName":"eupen","country":"Belgium","normalizedCountry":"belgium","subcountry":"Wallonia","geonameid":"2798573","cityStatus":"index_only","hasCoordinates":false,"isOfficialNetworkNode":false,"isE2EHub":false,"hubCandidate":false,"isDuplicate":false},{"id":"city:etterbeek:belgium:2798578","name":"Etterbeek","normalizedName":"etterbeek","country":"Belgium","normalizedCountry":"belgium","subcountry":"Brussels Capital","geonameid":"2798578","cityStatus":"index_only","hasCoordinates":false,"isOfficialNetworkNode":false,"isE2EHub":false,"hubCandidate":false,"isDuplicate":false},{"id":"city:ekeren:belgium:2798873","name":"Ekeren","normalizedName":"ekeren","country":"Belgium","normalizedCountry":"belgium","subcountry":"Flanders","geonameid":"2798873","cityStatus":"index_only","hasCoordinates":false,"isOfficialNetworkNode":false,"isE2EHub":false,"hubCandidate":false,"isDuplicate":false},{"id":"city:eeklo:belgium:2798987","name":"Eeklo","normalizedName":"eeklo","country":"Belgium","normalizedCountry":"belgium","subcountry":"Flanders","geonameid":"2798987","cityStatus":"index_only","hasCoordinates":false,"isOfficialNetworkNode":false,"isE2EHub":false,"hubCandidate":false,"isDuplicate":false},{"id":"city:edegem:belgium:2799007","name":"Edegem","normalizedName":"edegem","country":"Belgium","normalizedCountry":"belgium","subcountry":"Flanders","geonameid":"2799007","cityStatus":"index_only","hasCoordinates":false,"isOfficialNetworkNode":false,"isE2EHub":false,"hubCandidate":false,"isDuplicate":false},{"id":"city:duffel:belgium:2799090","name":"Duffel","normalizedName":"duffel","country":"Belgium","normalizedCountry":"belgium","subcountry":"Flanders","geonameid":"2799090","cityStatus":"index_only","hasCoordinates":false,"isOfficialNetworkNode":false,"isE2EHub":false,"hubCandidate":false,"isDuplicate":false},{"id":"city:dour:belgium:2799226","name":"Dour","normalizedName":"dour","country":"Belgium","normalizedCountry":"belgium","subcountry":"Wallonia","geonameid":"2799226","cityStatus":"index_only","hasCoordinates":false,"isOfficialNetworkNode":false,"isE2EHub":false,"hubCandidate":false,"isDuplicate":false},{"id":"city:dilbeek:belgium:2799365","name":"Dilbeek","normalizedName":"dilbeek","country":"Belgium","normalizedCountry":"belgium","subcountry":"Flanders","geonameid":"2799365","cityStatus":"index_only","hasCoordinates":false,"isOfficialNetworkNode":false,"isE2EHub":false,"hubCandidate":false,"isDuplicate":false},{"id":"city:diksmuide:belgium:2799369","name":"Diksmuide","normalizedName":"diksmuide","country":"Belgium","normalizedCountry":"belgium","subcountry":"Flanders","geonameid":"2799369","cityStatus":"index_only","hasCoordinates":false,"isOfficialNetworkNode":false,"isE2EHub":false,"hubCandidate":false,"isDuplicate":false},{"id":"city:diest:belgium:2799397","name":"Diest","normalizedName":"diest","country":"Belgium","normalizedCountry":"belgium","subcountry":"Flanders","geonameid":"2799397","cityStatus":"index_only","hasCoordinates":false,"isOfficialNetworkNode":false,"isE2EHub":false,"hubCandidate":false,"isDuplicate":false},{"id":"city:diepenbeek:belgium:2799412","name":"Diepenbeek","normalizedName":"diepenbeek","country":"Belgium","normalizedCountry":"belgium","subcountry":"Flanders","geonameid":"2799412","cityStatus":"index_only","hasCoordinates":false,"isOfficialNetworkNode":false,"isE2EHub":false,"hubCandidate":false,"isDuplicate":false},{"id":"city:deurne:belgium:2799478","name":"Deurne","normalizedName":"deurne","country":"Belgium","normalizedCountry":"belgium","subcountry":"Flanders","geonameid":"2799478","cityStatus":"index_only","hasCoordinates":false,"isOfficialNetworkNode":false,"isE2EHub":false,"hubCandidate":false,"isDuplicate":false},{"id":"city:destelbergen:belgium:2799496","name":"Destelbergen","normalizedName":"destelbergen","country":"Belgium","normalizedCountry":"belgium","subcountry":"Flanders","geonameid":"2799496","cityStatus":"index_only","hasCoordinates":false,"isOfficialNetworkNode":false,"isE2EHub":false,"hubCandidate":false,"isDuplicate":false},{"id":"city:dendermonde:belgium:2799645","name":"Dendermonde","normalizedName":"dendermonde","country":"Belgium","normalizedCountry":"belgium","subcountry":"Flanders","geonameid":"2799645","cityStatus":"index_only","hasCoordinates":false,"isOfficialNetworkNode":false,"isE2EHub":false,"hubCandidate":false,"isDuplicate":false},{"id":"city:denderleeuw:belgium:2799647","name":"Denderleeuw","normalizedName":"denderleeuw","country":"Belgium","normalizedCountry":"belgium","subcountry":"Flanders","geonameid":"2799647","cityStatus":"index_only","hasCoordinates":false,"isOfficialNetworkNode":false,"isE2EHub":false,"hubCandidate":false,"isDuplicate":false},{"id":"city:deinze:belgium:2799746","name":"Deinze","normalizedName":"deinze","country":"Belgium","normalizedCountry":"belgium","subcountry":"Flanders","geonameid":"2799746","cityStatus":"index_only","hasCoordinates":false,"isOfficialNetworkNode":false,"isE2EHub":false,"hubCandidate":false,"isDuplicate":false},{"id":"city:courcelles:belgium:2800063","name":"Courcelles","normalizedName":"courcelles","country":"Belgium","normalizedCountry":"belgium","subcountry":"Wallonia","geonameid":"2800063","cityStatus":"index_only","hasCoordinates":false,"isOfficialNetworkNode":false,"isE2EHub":false,"hubCandidate":false,"isDuplicate":false},{"id":"city:colfontaine:belgium:2800220","name":"Colfontaine","normalizedName":"colfontaine","country":"Belgium","normalizedCountry":"belgium","subcountry":"Wallonia","geonameid":"2800220","cityStatus":"index_only","hasCoordinates":false,"isOfficialNetworkNode":false,"isE2EHub":false,"hubCandidate":false,"isDuplicate":false},{"id":"city:chaudfontaine:belgium:2800438","name":"Chaudfontaine","normalizedName":"chaudfontaine","country":"Belgium","normalizedCountry":"belgium","subcountry":"Wallonia","geonameid":"2800438","cityStatus":"index_only","hasCoordinates":false,"isOfficialNetworkNode":false,"isE2EHub":false,"hubCandidate":false,"isDuplicate":false},{"id":"city:ch-telineau:belgium:2800445","name":"Ch\u00e2telineau","normalizedName":"ch-telineau","country":"Belgium","normalizedCountry":"belgium","subcountry":"Wallonia","geonameid":"2800445","cityStatus":"index_only","hasCoordinates":false,"isOfficialNetworkNode":false,"isE2EHub":false,"hubCandidate":false,"isDuplicate":false},{"id":"city:ch-telet:belgium:2800448","name":"Ch\u00e2telet","normalizedName":"ch-telet","country":"Belgium","normalizedCountry":"belgium","subcountry":"Wallonia","geonameid":"2800448","cityStatus":"index_only","hasCoordinates":false,"isOfficialNetworkNode":false,"isE2EHub":false,"hubCandidate":false,"isDuplicate":false},{"id":"city:charleroi:belgium:2800481","name":"Charleroi","normalizedName":"charleroi","country":"Belgium","normalizedCountry":"belgium","subcountry":"Wallonia","geonameid":"2800481","cityStatus":"index_only","hasCoordinates":false,"isOfficialNetworkNode":false,"isE2EHub":false,"hubCandidate":false,"isDuplicate":false},{"id":"city:brussels:belgium:2800866","name":"Brussels","normalizedName":"brussels","country":"Belgium","normalizedCountry":"belgium","subcountry":"Brussels Capital","geonameid":"2800866","cityStatus":"official_network_node","hasCoordinates":true,"isOfficialNetworkNode":true,"isE2EHub":false,"hubCandidate":true,"isDuplicate":false},{"id":"city:brugge:belgium:2800931","name":"Brugge","normalizedName":"brugge","country":"Belgium","normalizedCountry":"belgium","subcountry":"Flanders","geonameid":"2800931","cityStatus":"index_only","hasCoordinates":false,"isOfficialNetworkNode":false,"isE2EHub":false,"hubCandidate":false,"isDuplicate":false},{"id":"city:brasschaat:belgium:2801117","name":"Brasschaat","normalizedName":"brasschaat","country":"Belgium","normalizedCountry":"belgium","subcountry":"Flanders","geonameid":"2801117","cityStatus":"index_only","hasCoordinates":false,"isOfficialNetworkNode":false,"isE2EHub":false,"hubCandidate":false,"isDuplicate":false},{"id":"city:braine-le-comte:belgium:2801150","name":"Braine-le-Comte","normalizedName":"braine-le-comte","country":"Belgium","normalizedCountry":"belgium","subcountry":"Wallonia","geonameid":"2801150","cityStatus":"index_only","hasCoordinates":false,"isOfficialNetworkNode":false,"isE2EHub":false,"hubCandidate":false,"isDuplicate":false},{"id":"city:braine-l-alleud:belgium:2801154","name":"Braine-l'Alleud","normalizedName":"braine-l-alleud","country":"Belgium","normalizedCountry":"belgium","subcountry":"Wallonia","geonameid":"2801154","cityStatus":"index_only","hasCoordinates":false,"isOfficialNetworkNode":false,"isE2EHub":false,"hubCandidate":false,"isDuplicate":false},{"id":"city:boussu:belgium:2801226","name":"Boussu","normalizedName":"boussu","country":"Belgium","normalizedCountry":"belgium","subcountry":"Wallonia","geonameid":"2801226","cityStatus":"index_only","hasCoordinates":false,"isOfficialNetworkNode":false,"isE2EHub":false,"hubCandidate":false,"isDuplicate":false},{"id":"city:bornem:belgium:2801447","name":"Bornem","normalizedName":"bornem","country":"Belgium","normalizedCountry":"belgium","subcountry":"Flanders","geonameid":"2801447","cityStatus":"index_only","hasCoordinates":false,"isOfficialNetworkNode":false,"isE2EHub":false,"hubCandidate":false,"isDuplicate":false},{"id":"city:borgerhout:belgium:2801471","name":"Borgerhout","normalizedName":"borgerhout","country":"Belgium","normalizedCountry":"belgium","subcountry":"Flanders","geonameid":"2801471","cityStatus":"index_only","hasCoordinates":false,"isOfficialNetworkNode":false,"isE2EHub":false,"hubCandidate":false,"isDuplicate":false},{"id":"city:boom:belgium:2801494","name":"Boom","normalizedName":"boom","country":"Belgium","normalizedCountry":"belgium","subcountry":"Flanders","geonameid":"2801494","cityStatus":"index_only","hasCoordinates":false,"isOfficialNetworkNode":false,"isE2EHub":false,"hubCandidate":false,"isDuplicate":false},{"id":"city:blauwput:belgium:2801824","name":"Blauwput","normalizedName":"blauwput","country":"Belgium","normalizedCountry":"belgium","subcountry":"Flanders","geonameid":"2801824","cityStatus":"index_only","hasCoordinates":false,"isOfficialNetworkNode":false,"isE2EHub":false,"hubCandidate":false,"isDuplicate":false},{"id":"city:blankenberge:belgium:2801858","name":"Blankenberge","normalizedName":"blankenberge","country":"Belgium","normalizedCountry":"belgium","subcountry":"Flanders","geonameid":"2801858","cityStatus":"index_only","hasCoordinates":false,"isOfficialNetworkNode":false,"isE2EHub":false,"hubCandidate":false,"isDuplicate":false},{"id":"city:binche:belgium:2801922","name":"Binche","normalizedName":"binche","country":"Belgium","normalizedCountry":"belgium","subcountry":"Wallonia","geonameid":"2801922","cityStatus":"index_only","hasCoordinates":false,"isOfficialNetworkNode":false,"isE2EHub":false,"hubCandidate":false,"isDuplicate":false},{"id":"city:bilzen:belgium:2801924","name":"Bilzen","normalizedName":"bilzen","country":"Belgium","normalizedCountry":"belgium","subcountry":"Flanders","geonameid":"2801924","cityStatus":"index_only","hasCoordinates":false,"isOfficialNetworkNode":false,"isE2EHub":false,"hubCandidate":false,"isDuplicate":false},{"id":"city:beveren:belgium:2802031","name":"Beveren","normalizedName":"beveren","country":"Belgium","normalizedCountry":"belgium","subcountry":"Flanders","geonameid":"2802031","cityStatus":"index_only","hasCoordinates":false,"isOfficialNetworkNode":false,"isE2EHub":false,"hubCandidate":false,"isDuplicate":false},{"id":"city:bevere:belgium:2802039","name":"Bevere","normalizedName":"bevere","country":"Belgium","normalizedCountry":"belgium","subcountry":"Flanders","geonameid":"2802039","cityStatus":"index_only","hasCoordinates":false,"isOfficialNetworkNode":false,"isE2EHub":false,"hubCandidate":false,"isDuplicate":false},{"id":"city:beringen:belgium:2802170","name":"Beringen","normalizedName":"beringen","country":"Belgium","normalizedCountry":"belgium","subcountry":"Flanders","geonameid":"2802170","cityStatus":"index_only","hasCoordinates":false,"isOfficialNetworkNode":false,"isE2EHub":false,"hubCandidate":false,"isDuplicate":false},{"id":"city:berchem-sainte-agathe:belgium:2802247","name":"Berchem-Sainte-Agathe","normalizedName":"berchem-sainte-agathe","country":"Belgium","normalizedCountry":"belgium","subcountry":"Brussels Capital","geonameid":"2802247","cityStatus":"index_only","hasCoordinates":false,"isOfficialNetworkNode":false,"isE2EHub":false,"hubCandidate":false,"isDuplicate":false},{"id":"city:berchem:belgium:2802249","name":"Berchem","normalizedName":"berchem","country":"Belgium","normalizedCountry":"belgium","subcountry":"Flanders","geonameid":"2802249","cityStatus":"index_only","hasCoordinates":false,"isOfficialNetworkNode":false,"isE2EHub":false,"hubCandidate":false,"isDuplicate":false},{"id":"city:beersel:belgium:2802433","name":"Beersel","normalizedName":"beersel","country":"Belgium","normalizedCountry":"belgium","subcountry":"Flanders","geonameid":"2802433","cityStatus":"index_only","hasCoordinates":false,"isOfficialNetworkNode":false,"isE2EHub":false,"hubCandidate":false,"isDuplicate":false},{"id":"city:beerse:belgium:2802435","name":"Beerse","normalizedName":"beerse","country":"Belgium","normalizedCountry":"belgium","subcountry":"Flanders","geonameid":"2802435","cityStatus":"index_only","hasCoordinates":false,"isOfficialNetworkNode":false,"isE2EHub":false,"hubCandidate":false,"isDuplicate":false},{"id":"city:balen:belgium:2802743","name":"Balen","normalizedName":"balen","country":"Belgium","normalizedCountry":"belgium","subcountry":"Flanders","geonameid":"2802743","cityStatus":"index_only","hasCoordinates":false,"isOfficialNetworkNode":false,"isE2EHub":false,"hubCandidate":false,"isDuplicate":false},{"id":"city:auderghem:belgium:2802960","name":"Auderghem","normalizedName":"auderghem","country":"Belgium","normalizedCountry":"belgium","subcountry":"Brussels Capital","geonameid":"2802960","cityStatus":"index_only","hasCoordinates":false,"isOfficialNetworkNode":false,"isE2EHub":false,"hubCandidate":false,"isDuplicate":false},{"id":"city:ath:belgium:2803010","name":"Ath","normalizedName":"ath","country":"Belgium","normalizedCountry":"belgium","subcountry":"Wallonia","geonameid":"2803010","cityStatus":"index_only","hasCoordinates":false,"isOfficialNetworkNode":false,"isE2EHub":false,"hubCandidate":false,"isDuplicate":false},{"id":"city:assebroek:belgium:2803030","name":"Assebroek","normalizedName":"assebroek","country":"Belgium","normalizedCountry":"belgium","subcountry":"Flanders","geonameid":"2803030","cityStatus":"index_only","hasCoordinates":false,"isOfficialNetworkNode":false,"isE2EHub":false,"hubCandidate":false,"isDuplicate":false},{"id":"city:asse:belgium:2803033","name":"Asse","normalizedName":"asse","country":"Belgium","normalizedCountry":"belgium","subcountry":"Flanders","geonameid":"2803033","cityStatus":"index_only","hasCoordinates":false,"isOfficialNetworkNode":false,"isE2EHub":false,"hubCandidate":false,"isDuplicate":false},{"id":"city:arlon:belgium:2803073","name":"Arlon","normalizedName":"arlon","country":"Belgium","normalizedCountry":"belgium","subcountry":"Wallonia","geonameid":"2803073","cityStatus":"index_only","hasCoordinates":false,"isOfficialNetworkNode":false,"isE2EHub":false,"hubCandidate":false,"isDuplicate":false},{"id":"city:antwerpen:belgium:2803138","name":"Antwerpen","normalizedName":"antwerpen","country":"Belgium","normalizedCountry":"belgium","subcountry":"Flanders","geonameid":"2803138","cityStatus":"index_only","hasCoordinates":false,"isOfficialNetworkNode":false,"isE2EHub":false,"hubCandidate":false,"isDuplicate":false},{"id":"city:ans:belgium:2803160","name":"Ans","normalizedName":"ans","country":"Belgium","normalizedCountry":"belgium","subcountry":"Wallonia","geonameid":"2803160","cityStatus":"index_only","hasCoordinates":false,"isOfficialNetworkNode":false,"isE2EHub":false,"hubCandidate":false,"isDuplicate":false},{"id":"city:anderlecht:belgium:2803201","name":"Anderlecht","normalizedName":"anderlecht","country":"Belgium","normalizedCountry":"belgium","subcountry":"Brussels Capital","geonameid":"2803201","cityStatus":"index_only","hasCoordinates":false,"isOfficialNetworkNode":false,"isE2EHub":false,"hubCandidate":false,"isDuplicate":false},{"id":"city:andenne:belgium:2803204","name":"Andenne","normalizedName":"andenne","country":"Belgium","normalizedCountry":"belgium","subcountry":"Wallonia","geonameid":"2803204","cityStatus":"index_only","hasCoordinates":false,"isOfficialNetworkNode":false,"isE2EHub":false,"hubCandidate":false,"isDuplicate":false},{"id":"city:aarschot:belgium:2803429","name":"Aarschot","normalizedName":"aarschot","country":"Belgium","normalizedCountry":"belgium","subcountry":"Flanders","geonameid":"2803429","cityStatus":"index_only","hasCoordinates":false,"isOfficialNetworkNode":false,"isE2EHub":false,"hubCandidate":false,"isDuplicate":false},{"id":"city:aalter:belgium:2803443","name":"Aalter","normalizedName":"aalter","country":"Belgium","normalizedCountry":"belgium","subcountry":"Flanders","geonameid":"2803443","cityStatus":"index_only","hasCoordinates":false,"isOfficialNetworkNode":false,"isE2EHub":false,"hubCandidate":false,"isDuplicate":false},{"id":"city:aalst:belgium:2803448","name":"Aalst","normalizedName":"aalst","country":"Belgium","normalizedCountry":"belgium","subcountry":"Flanders","geonameid":"2803448","cityStatus":"index_only","hasCoordinates":false,"isOfficialNetworkNode":false,"isE2EHub":false,"hubCandidate":false,"isDuplicate":false}]