[{"id":"city:verrettes:haiti:3716044","name":"Verrettes","normalizedName":"verrettes","country":"Haiti","normalizedCountry":"haiti","subcountry":"Artibonite","geonameid":"3716044","cityStatus":"index_only","hasCoordinates":false,"isOfficialNetworkNode":false,"isE2EHub":false,"hubCandidate":false,"isDuplicate":false},{"id":"city:thomazeau:haiti:3716667","name":"Thomazeau","normalizedName":"thomazeau","country":"Haiti","normalizedCountry":"haiti","subcountry":"Ouest","geonameid":"3716667","cityStatus":"index_only","hasCoordinates":false,"isOfficialNetworkNode":false,"isE2EHub":false,"hubCandidate":false,"isDuplicate":false},{"id":"city:terrier-rouge:haiti:3716737","name":"Terrier Rouge","normalizedName":"terrier-rouge","country":"Haiti","normalizedCountry":"haiti","subcountry":"Nord-Est","geonameid":"3716737","cityStatus":"index_only","hasCoordinates":false,"isOfficialNetworkNode":false,"isE2EHub":false,"hubCandidate":false,"isDuplicate":false},{"id":"city:saint-rapha-l:haiti:3717546","name":"Saint-Rapha\u00ebl","normalizedName":"saint-rapha-l","country":"Haiti","normalizedCountry":"haiti","subcountry":"Nord","geonameid":"3717546","cityStatus":"index_only","hasCoordinates":false,"isOfficialNetworkNode":false,"isE2EHub":false,"hubCandidate":false,"isDuplicate":false},{"id":"city:saint-michel-de-l-atalaye:haiti:3717560","name":"Saint-Michel de l'Atalaye","normalizedName":"saint-michel-de-l-atalaye","country":"Haiti","normalizedCountry":"haiti","subcountry":"Artibonite","geonameid":"3717560","cityStatus":"index_only","hasCoordinates":false,"isOfficialNetworkNode":false,"isE2EHub":false,"hubCandidate":false,"isDuplicate":false},{"id":"city:saint-marc:haiti:3717588","name":"Saint-Marc","normalizedName":"saint-marc","country":"Haiti","normalizedCountry":"haiti","subcountry":"Artibonite","geonameid":"3717588","cityStatus":"index_only","hasCoordinates":false,"isOfficialNetworkNode":false,"isE2EHub":false,"hubCandidate":false,"isDuplicate":false},{"id":"city:port-de-paix:haiti:3718420","name":"Port-de-Paix","normalizedName":"port-de-paix","country":"Haiti","normalizedCountry":"haiti","subcountry":"Nord-Ouest","geonameid":"3718420","cityStatus":"index_only","hasCoordinates":false,"isOfficialNetworkNode":false,"isE2EHub":false,"hubCandidate":false,"isDuplicate":false},{"id":"city:port-au-prince:haiti:3718426","name":"Port-au-Prince","normalizedName":"port-au-prince","country":"Haiti","normalizedCountry":"haiti","subcountry":"Ouest","geonameid":"3718426","cityStatus":"index_only","hasCoordinates":false,"isOfficialNetworkNode":false,"isE2EHub":false,"hubCandidate":false,"isDuplicate":false},{"id":"city:tigwav:haiti:3718962","name":"Tigwav","normalizedName":"tigwav","country":"Haiti","normalizedCountry":"haiti","subcountry":"Ouest","geonameid":"3718962","cityStatus":"index_only","hasCoordinates":false,"isOfficialNetworkNode":false,"isE2EHub":false,"hubCandidate":false,"isDuplicate":false},{"id":"city:p-tionville:haiti:3719028","name":"P\u00e9tionville","normalizedName":"p-tionville","country":"Haiti","normalizedCountry":"haiti","subcountry":"Ouest","geonameid":"3719028","cityStatus":"index_only","hasCoordinates":false,"isOfficialNetworkNode":false,"isE2EHub":false,"hubCandidate":false,"isDuplicate":false},{"id":"city:mirago-ne:haiti:3720824","name":"Mirago\u00e2ne","normalizedName":"mirago-ne","country":"Haiti","normalizedCountry":"haiti","subcountry":"Nippes","geonameid":"3720824","cityStatus":"index_only","hasCoordinates":false,"isOfficialNetworkNode":false,"isE2EHub":false,"hubCandidate":false,"isDuplicate":false},{"id":"city:lenbe:haiti:3722124","name":"Lenbe","normalizedName":"lenbe","country":"Haiti","normalizedCountry":"haiti","subcountry":"Nord","geonameid":"3722124","cityStatus":"index_only","hasCoordinates":false,"isOfficialNetworkNode":false,"isE2EHub":false,"hubCandidate":false,"isDuplicate":false},{"id":"city:l-og-ne:haiti:3722286","name":"L\u00e9og\u00e2ne","normalizedName":"l-og-ne","country":"Haiti","normalizedCountry":"haiti","subcountry":"Ouest","geonameid":"3722286","cityStatus":"index_only","hasCoordinates":false,"isOfficialNetworkNode":false,"isE2EHub":false,"hubCandidate":false,"isDuplicate":false},{"id":"city:kenscoff:haiti:3723440","name":"Kenscoff","normalizedName":"kenscoff","country":"Haiti","normalizedCountry":"haiti","subcountry":"Ouest","geonameid":"3723440","cityStatus":"index_only","hasCoordinates":false,"isOfficialNetworkNode":false,"isE2EHub":false,"hubCandidate":false,"isDuplicate":false},{"id":"city:j-r-mie:haiti:3723593","name":"J\u00e9r\u00e9mie","normalizedName":"j-r-mie","country":"Haiti","normalizedCountry":"haiti","subcountry":"Grand'Anse","geonameid":"3723593","cityStatus":"index_only","hasCoordinates":false,"isOfficialNetworkNode":false,"isE2EHub":false,"hubCandidate":false,"isDuplicate":false},{"id":"city:jacmel:haiti:3723779","name":"Jacmel","normalizedName":"jacmel","country":"Haiti","normalizedCountry":"haiti","subcountry":"Sud-Est","geonameid":"3723779","cityStatus":"index_only","hasCoordinates":false,"isOfficialNetworkNode":false,"isE2EHub":false,"hubCandidate":false,"isDuplicate":false},{"id":"city:hinche:haiti:3723841","name":"Hinche","normalizedName":"hinche","country":"Haiti","normalizedCountry":"haiti","subcountry":"Centre","geonameid":"3723841","cityStatus":"index_only","hasCoordinates":false,"isOfficialNetworkNode":false,"isE2EHub":false,"hubCandidate":false,"isDuplicate":false},{"id":"city:gressier:haiti:3724233","name":"Gressier","normalizedName":"gressier","country":"Haiti","normalizedCountry":"haiti","subcountry":"Ouest","geonameid":"3724233","cityStatus":"index_only","hasCoordinates":false,"isOfficialNetworkNode":false,"isE2EHub":false,"hubCandidate":false,"isDuplicate":false},{"id":"city:grand-gosier:haiti:3724331","name":"Grand Gosier","normalizedName":"grand-gosier","country":"Haiti","normalizedCountry":"haiti","subcountry":"Sud-Est","geonameid":"3724331","cityStatus":"index_only","hasCoordinates":false,"isOfficialNetworkNode":false,"isE2EHub":false,"hubCandidate":false,"isDuplicate":false},{"id":"city:grangwav:haiti:3724337","name":"Grangwav","normalizedName":"grangwav","country":"Haiti","normalizedCountry":"haiti","subcountry":"Ouest","geonameid":"3724337","cityStatus":"index_only","hasCoordinates":false,"isOfficialNetworkNode":false,"isE2EHub":false,"hubCandidate":false,"isDuplicate":false},{"id":"city:gona-ves:haiti:3724696","name":"Gona\u00efves","normalizedName":"gona-ves","country":"Haiti","normalizedCountry":"haiti","subcountry":"Artibonite","geonameid":"3724696","cityStatus":"index_only","hasCoordinates":false,"isOfficialNetworkNode":false,"isE2EHub":false,"hubCandidate":false,"isDuplicate":false},{"id":"city:fond-parisien:haiti:3725276","name":"Fond Parisien","normalizedName":"fond-parisien","country":"Haiti","normalizedCountry":"haiti","subcountry":"Ouest","geonameid":"3725276","cityStatus":"index_only","hasCoordinates":false,"isOfficialNetworkNode":false,"isE2EHub":false,"hubCandidate":false,"isDuplicate":false},{"id":"city:d-sarmes:haiti:3726674","name":"D\u00e9sarmes","normalizedName":"d-sarmes","country":"Haiti","normalizedCountry":"haiti","subcountry":"Artibonite","geonameid":"3726674","cityStatus":"index_only","hasCoordinates":false,"isOfficialNetworkNode":false,"isE2EHub":false,"hubCandidate":false,"isDuplicate":false},{"id":"city:delmas:haiti:3726786","name":"Delmas","normalizedName":"delmas","country":"Haiti","normalizedCountry":"haiti","subcountry":"Ouest","geonameid":"3726786","cityStatus":"index_only","hasCoordinates":false,"isOfficialNetworkNode":false,"isE2EHub":false,"hubCandidate":false,"isDuplicate":false},{"id":"city:croix-des-bouquets:haiti:3727135","name":"Croix-des-Bouquets","normalizedName":"croix-des-bouquets","country":"Haiti","normalizedCountry":"haiti","subcountry":"Ouest","geonameid":"3727135","cityStatus":"index_only","hasCoordinates":false,"isOfficialNetworkNode":false,"isE2EHub":false,"hubCandidate":false,"isDuplicate":false},{"id":"city:les-cayes:haiti:3728097","name":"Les Cayes","normalizedName":"les-cayes","country":"Haiti","normalizedCountry":"haiti","subcountry":"Sud","geonameid":"3728097","cityStatus":"index_only","hasCoordinates":false,"isOfficialNetworkNode":false,"isE2EHub":false,"hubCandidate":false,"isDuplicate":false},{"id":"city:cap-ha-tien:haiti:3728474","name":"Cap-Ha\u00eftien","normalizedName":"cap-ha-tien","country":"Haiti","normalizedCountry":"haiti","subcountry":"Nord","geonameid":"3728474","cityStatus":"index_only","hasCoordinates":false,"isOfficialNetworkNode":false,"isE2EHub":false,"hubCandidate":false,"isDuplicate":false},{"id":"city:arcahaie:haiti:3731088","name":"Arcahaie","normalizedName":"arcahaie","country":"Haiti","normalizedCountry":"haiti","subcountry":"Ouest","geonameid":"3731088","cityStatus":"index_only","hasCoordinates":false,"isOfficialNetworkNode":false,"isE2EHub":false,"hubCandidate":false,"isDuplicate":false},{"id":"city:ti-port-de-paix:haiti:3740016","name":"Ti Port-de-Paix","normalizedName":"ti-port-de-paix","country":"Haiti","normalizedCountry":"haiti","subcountry":"Nord-Ouest","geonameid":"3740016","cityStatus":"index_only","hasCoordinates":false,"isOfficialNetworkNode":false,"isE2EHub":false,"hubCandidate":false,"isDuplicate":false},{"id":"city:carrefour:haiti:6201369","name":"Carrefour","normalizedName":"carrefour","country":"Haiti","normalizedCountry":"haiti","subcountry":"Ouest","geonameid":"6201369","cityStatus":"index_only","hasCoordinates":false,"isOfficialNetworkNode":false,"isE2EHub":false,"hubCandidate":false,"isDuplicate":false}]