[{"id":"city:moutsamoudou:comoros:921753","name":"Moutsamoudou","normalizedName":"moutsamoudou","country":"Comoros","normalizedCountry":"comoros","subcountry":"Anjouan","geonameid":"921753","cityStatus":"index_only","hasCoordinates":false,"isOfficialNetworkNode":false,"isE2EHub":false,"hubCandidate":false,"isDuplicate":false},{"id":"city:moroni:comoros:921772","name":"Moroni","normalizedName":"moroni","country":"Comoros","normalizedCountry":"comoros","subcountry":"Grande Comore","geonameid":"921772","cityStatus":"index_only","hasCoordinates":false,"isOfficialNetworkNode":false,"isE2EHub":false,"hubCandidate":false,"isDuplicate":false},{"id":"city:fomboni:comoros:921889","name":"Fomboni","normalizedName":"fomboni","country":"Comoros","normalizedCountry":"comoros","subcountry":"Moheli","geonameid":"921889","cityStatus":"index_only","hasCoordinates":false,"isOfficialNetworkNode":false,"isE2EHub":false,"hubCandidate":false,"isDuplicate":false}]