[{"id":"city:sur:oman:286245","name":"Sur","normalizedName":"sur","country":"Oman","normalizedCountry":"oman","subcountry":"Southeastern Governorate","geonameid":"286245","cityStatus":"index_only","hasCoordinates":false,"isOfficialNetworkNode":false,"isE2EHub":false,"hubCandidate":false,"isDuplicate":false},{"id":"city:sohar:oman:286282","name":"Sohar","normalizedName":"sohar","country":"Oman","normalizedCountry":"oman","subcountry":"Al Batinah North","geonameid":"286282","cityStatus":"index_only","hasCoordinates":false,"isOfficialNetworkNode":false,"isE2EHub":false,"hubCandidate":false,"isDuplicate":false},{"id":"city:suf-lat-sam-il:oman:286293","name":"Suf\u0101lat Sam\u0101\u2019il","normalizedName":"suf-lat-sam-il","country":"Oman","normalizedCountry":"oman","subcountry":"Ad Dakhiliyah","geonameid":"286293","cityStatus":"index_only","hasCoordinates":false,"isOfficialNetworkNode":false,"isE2EHub":false,"hubCandidate":false,"isDuplicate":false},{"id":"city:shin:oman:286402","name":"Shin\u0101\u015f","normalizedName":"shin","country":"Oman","normalizedCountry":"oman","subcountry":"Al Batinah North","geonameid":"286402","cityStatus":"index_only","hasCoordinates":false,"isOfficialNetworkNode":false,"isE2EHub":false,"hubCandidate":false,"isDuplicate":false},{"id":"city:sam-il:oman:286590","name":"Sam\u0101\u2019il","normalizedName":"sam-il","country":"Oman","normalizedCountry":"oman","subcountry":"Ad Dakhiliyah","geonameid":"286590","cityStatus":"index_only","hasCoordinates":false,"isOfficialNetworkNode":false,"isE2EHub":false,"hubCandidate":false,"isDuplicate":false},{"id":"city:al-lah:oman:286621","name":"\u015eal\u0101lah","normalizedName":"al-lah","country":"Oman","normalizedCountry":"oman","subcountry":"Dhofar","geonameid":"286621","cityStatus":"index_only","hasCoordinates":false,"isOfficialNetworkNode":false,"isE2EHub":false,"hubCandidate":false,"isDuplicate":false},{"id":"city:a-am:oman:286647","name":"\u015ea\u1e29am","normalizedName":"a-am","country":"Oman","normalizedCountry":"oman","subcountry":"Al Batinah North","geonameid":"286647","cityStatus":"index_only","hasCoordinates":false,"isOfficialNetworkNode":false,"isE2EHub":false,"hubCandidate":false,"isDuplicate":false},{"id":"city:qurayy-t:oman:286839","name":"Qurayy\u0101t","normalizedName":"qurayy-t","country":"Oman","normalizedCountry":"oman","subcountry":"Muscat","geonameid":"286839","cityStatus":"index_only","hasCoordinates":false,"isOfficialNetworkNode":false,"isE2EHub":false,"hubCandidate":false,"isDuplicate":false},{"id":"city:nizw:oman:286987","name":"Nizw\u00e1","normalizedName":"nizw","country":"Oman","normalizedCountry":"oman","subcountry":"Ad Dakhiliyah","geonameid":"286987","cityStatus":"index_only","hasCoordinates":false,"isOfficialNetworkNode":false,"isE2EHub":false,"hubCandidate":false,"isDuplicate":false},{"id":"city:muscat:oman:287286","name":"Muscat","normalizedName":"muscat","country":"Oman","normalizedCountry":"oman","subcountry":"Muscat","geonameid":"287286","cityStatus":"official_network_node","hasCoordinates":true,"isOfficialNetworkNode":true,"isE2EHub":false,"hubCandidate":false,"isDuplicate":false},{"id":"city:khasab:oman:287614","name":"Khasab","normalizedName":"khasab","country":"Oman","normalizedCountry":"oman","subcountry":"Musandam Governorate","geonameid":"287614","cityStatus":"index_only","hasCoordinates":false,"isOfficialNetworkNode":false,"isE2EHub":false,"hubCandidate":false,"isDuplicate":false},{"id":"city:izk:oman:287814","name":"Izk\u012b","normalizedName":"izk","country":"Oman","normalizedCountry":"oman","subcountry":"Ad Dakhiliyah","geonameid":"287814","cityStatus":"index_only","hasCoordinates":false,"isOfficialNetworkNode":false,"isE2EHub":false,"hubCandidate":false,"isDuplicate":false},{"id":"city:ibr:oman:287830","name":"\u2018Ibr\u012b","normalizedName":"ibr","country":"Oman","normalizedCountry":"oman","subcountry":"Ad Dhahirah","geonameid":"287830","cityStatus":"index_only","hasCoordinates":false,"isOfficialNetworkNode":false,"isE2EHub":false,"hubCandidate":false,"isDuplicate":true},{"id":"city:ibr:oman:287832","name":"Ibr\u0101\u2019","normalizedName":"ibr","country":"Oman","normalizedCountry":"oman","subcountry":"Northeastern Governorate","geonameid":"287832","cityStatus":"index_only","hasCoordinates":false,"isOfficialNetworkNode":false,"isE2EHub":false,"hubCandidate":false,"isDuplicate":true},{"id":"city:bidbid:oman:288721","name":"Bidbid","normalizedName":"bidbid","country":"Oman","normalizedCountry":"oman","subcountry":"Ad Dakhiliyah","geonameid":"288721","cityStatus":"index_only","hasCoordinates":false,"isOfficialNetworkNode":false,"isE2EHub":false,"hubCandidate":false,"isDuplicate":false},{"id":"city:bawshar:oman:288764","name":"Bawshar","normalizedName":"bawshar","country":"Oman","normalizedCountry":"oman","subcountry":"Muscat","geonameid":"288764","cityStatus":"index_only","hasCoordinates":false,"isOfficialNetworkNode":false,"isE2EHub":false,"hubCandidate":false,"isDuplicate":false},{"id":"city:bark:oman:288789","name":"Bark\u0101\u2019","normalizedName":"bark","country":"Oman","normalizedCountry":"oman","subcountry":"Al Batinah South","geonameid":"288789","cityStatus":"index_only","hasCoordinates":false,"isOfficialNetworkNode":false,"isE2EHub":false,"hubCandidate":false,"isDuplicate":false},{"id":"city:bahl:oman:288899","name":"Bahl\u0101\u2019","normalizedName":"bahl","country":"Oman","normalizedCountry":"oman","subcountry":"Ad Dakhiliyah","geonameid":"288899","cityStatus":"index_only","hasCoordinates":false,"isOfficialNetworkNode":false,"isE2EHub":false,"hubCandidate":false,"isDuplicate":false},{"id":"city:bad-yah:oman:288902","name":"Bad\u012byah","normalizedName":"bad-yah","country":"Oman","normalizedCountry":"oman","subcountry":"Northeastern Governorate","geonameid":"288902","cityStatus":"index_only","hasCoordinates":false,"isOfficialNetworkNode":false,"isE2EHub":false,"hubCandidate":false,"isDuplicate":false},{"id":"city:as-suwayq:oman:288955","name":"As Suwayq","normalizedName":"as-suwayq","country":"Oman","normalizedCountry":"oman","subcountry":"Al Batinah North","geonameid":"288955","cityStatus":"index_only","hasCoordinates":false,"isOfficialNetworkNode":false,"isE2EHub":false,"hubCandidate":false,"isDuplicate":false},{"id":"city:seeb:oman:288967","name":"Seeb","normalizedName":"seeb","country":"Oman","normalizedCountry":"oman","subcountry":"Muscat","geonameid":"288967","cityStatus":"index_only","hasCoordinates":false,"isOfficialNetworkNode":false,"isE2EHub":false,"hubCandidate":false,"isDuplicate":false},{"id":"city:rustaq:oman:289011","name":"Rustaq","normalizedName":"rustaq","country":"Oman","normalizedCountry":"oman","subcountry":"Al Batinah South","geonameid":"289011","cityStatus":"index_only","hasCoordinates":false,"isOfficialNetworkNode":false,"isE2EHub":false,"hubCandidate":false,"isDuplicate":false},{"id":"city:liw:oman:289174","name":"Liw\u00e1","normalizedName":"liw","country":"Oman","normalizedCountry":"oman","subcountry":"Al Batinah North","geonameid":"289174","cityStatus":"index_only","hasCoordinates":false,"isOfficialNetworkNode":false,"isE2EHub":false,"hubCandidate":false,"isDuplicate":false},{"id":"city:al-kh-b-rah:oman:289199","name":"Al Kh\u0101b\u016brah","normalizedName":"al-kh-b-rah","country":"Oman","normalizedCountry":"oman","subcountry":"Al Batinah North","geonameid":"289199","cityStatus":"index_only","hasCoordinates":false,"isOfficialNetworkNode":false,"isE2EHub":false,"hubCandidate":false,"isDuplicate":false},{"id":"city:al-buraym:oman:289317","name":"Al Buraym\u012b","normalizedName":"al-buraym","country":"Oman","normalizedCountry":"oman","subcountry":"Al Buraimi","geonameid":"289317","cityStatus":"index_only","hasCoordinates":false,"isOfficialNetworkNode":false,"isE2EHub":false,"hubCandidate":false,"isDuplicate":false},{"id":"city:adam:oman:289433","name":"Adam","normalizedName":"adam","country":"Oman","normalizedCountry":"oman","subcountry":"Ad Dakhiliyah","geonameid":"289433","cityStatus":"index_only","hasCoordinates":false,"isOfficialNetworkNode":false,"isE2EHub":false,"hubCandidate":false,"isDuplicate":false},{"id":"city:yanqul:oman:411849","name":"Yanqul","normalizedName":"yanqul","country":"Oman","normalizedCountry":"oman","subcountry":"Ad Dhahirah","geonameid":"411849","cityStatus":"index_only","hasCoordinates":false,"isOfficialNetworkNode":false,"isE2EHub":false,"hubCandidate":false,"isDuplicate":false}]