{"andorra":{"file":"chunks/cities_andorra.json","count":2,"sample":"les Escaldes"},"united-arab-emirates":{"file":"chunks/cities_united-arab-emirates.json","count":63,"sample":"War\u012bs\u0101n"},"afghanistan":{"file":"chunks/cities_afghanistan.json","count":54,"sample":"Zaranj"},"antigua-and-barbuda":{"file":"chunks/cities_antigua-and-barbuda.json","count":1,"sample":"Saint John\u2019s"},"anguilla":{"file":"chunks/cities_anguilla.json","count":1,"sample":"The Valley"},"albania":{"file":"chunks/cities_albania.json","count":23,"sample":"Sarand\u00eb"},"armenia":{"file":"chunks/cities_armenia.json","count":29,"sample":"Kapan"},"angola":{"file":"chunks/cities_angola.json","count":131,"sample":"Saurimo"},"argentina":{"file":"chunks/cities_argentina.json","count":257,"sample":"Z\u00e1rate"},"american-samoa":{"file":"chunks/cities_american-samoa.json","count":1,"sample":"Pago Pago"},"austria":{"file":"chunks/cities_austria.json","count":64,"sample":"D\u00f6bling"},"australia":{"file":"chunks/cities_australia.json","count":311,"sample":"Scarborough"},"aruba":{"file":"chunks/cities_aruba.json","count":4,"sample":"Tanki Leendert"},"land-islands":{"file":"chunks/cities_land-islands.json","count":1,"sample":"Mariehamn"},"azerbaijan":{"file":"chunks/cities_azerbaijan.json","count":58,"sample":"\u018fhm\u0259db\u0259yli"},"bosnia-and-herzegovina":{"file":"chunks/cities_bosnia-and-herzegovina.json","count":23,"sample":"Zenica"},"barbados":{"file":"chunks/cities_barbados.json","count":1,"sample":"Bridgetown"},"bangladesh":{"file":"chunks/cities_bangladesh.json","count":137,"sample":"Th\u0101kurgaon"},"belgium":{"file":"chunks/cities_belgium.json","count":223,"sample":"Zwijndrecht"},"burkina-faso":{"file":"chunks/cities_burkina-faso.json","count":74,"sample":"Zorgo"},"bulgaria":{"file":"chunks/cities_bulgaria.json","count":56,"sample":"Yambol"},"bahrain":{"file":"chunks/cities_bahrain.json","count":8,"sample":"Sitrah"},"burundi":{"file":"chunks/cities_burundi.json","count":14,"sample":"Vyanda"},"benin":{"file":"chunks/cities_benin.json","count":66,"sample":"Zinvi\u00e9"},"saint-barth-lemy":{"file":"chunks/cities_saint-barth-lemy.json","count":1,"sample":"Gustavia"},"bermuda":{"file":"chunks/cities_bermuda.json","count":1,"sample":"Hamilton"},"brunei-darussalam":{"file":"chunks/cities_brunei-darussalam.json","count":8,"sample":"Tutong"},"bolivia-plurinational-state-of":{"file":"chunks/cities_bolivia-plurinational-state-of.json","count":39,"sample":"Yacuiba"},"bonaire-sint-eustatius-and-saba":{"file":"chunks/cities_bonaire-sint-eustatius-and-saba.json","count":1,"sample":"Kralendijk"},"brazil":{"file":"chunks/cities_brazil.json","count":2345,"sample":"Vitorino Freire"},"bahamas":{"file":"chunks/cities_bahamas.json","count":4,"sample":"Nassau"},"bhutan":{"file":"chunks/cities_bhutan.json","count":4,"sample":"Thimphu"},"botswana":{"file":"chunks/cities_botswana.json","count":25,"sample":"Tonota"},"belarus":{"file":"chunks/cities_belarus.json","count":57,"sample":"Horad Zhodzina"},"belize":{"file":"chunks/cities_belize.json","count":4,"sample":"San Pedro"},"canada":{"file":"chunks/cities_canada.json","count":504,"sample":"Abbotsford"},"cocos-keeling-islands":{"file":"chunks/cities_cocos-keeling-islands.json","count":1,"sample":"West Island"},"congo-the-democratic-republic-of-the":{"file":"chunks/cities_congo-the-democratic-republic-of-the.json","count":114,"sample":"Yangambi"},"central-african-republic":{"file":"chunks/cities_central-african-republic.json","count":32,"sample":"Zemio"},"congo":{"file":"chunks/cities_congo.json","count":23,"sample":"Sibiti"},"switzerland":{"file":"chunks/cities_switzerland.json","count":95,"sample":"Z\u00fcrich"},"c-te-d-ivoire":{"file":"chunks/cities_c-te-d-ivoire.json","count":183,"sample":"Zu\u00e9noula"},"cook-islands":{"file":"chunks/cities_cook-islands.json","count":1,"sample":"Avarua"},"chile":{"file":"chunks/cities_chile.json","count":146,"sample":"Vi\u00f1a del Mar"},"cameroon":{"file":"chunks/cities_cameroon.json","count":87,"sample":"Yokadouma"},"china":{"file":"chunks/cities_china.json","count":2093,"sample":"Zhefang"},"colombia":{"file":"chunks/cities_colombia.json","count":319,"sample":"Zipaquir\u00e1"},"costa-rica":{"file":"chunks/cities_costa-rica.json","count":41,"sample":"Turrialba"},"cuba":{"file":"chunks/cities_cuba.json","count":140,"sample":"Yara"},"cabo-verde":{"file":"chunks/cities_cabo-verde.json","count":4,"sample":"Praia"},"cura-ao":{"file":"chunks/cities_cura-ao.json","count":2,"sample":"Willemstad"},"christmas-island":{"file":"chunks/cities_christmas-island.json","count":1,"sample":"Flying Fish Cove"},"cyprus":{"file":"chunks/cities_cyprus.json","count":15,"sample":"Protaras"},"czechia":{"file":"chunks/cities_czechia.json","count":125,"sample":"Dv\u016fr Kr\u00e1lov\u00e9 nad Labem"},"germany":{"file":"chunks/cities_germany.json","count":1139,"sample":"Zwickau"},"djibouti":{"file":"chunks/cities_djibouti.json","count":6,"sample":"Tadjoura"},"denmark":{"file":"chunks/cities_denmark.json","count":64,"sample":"Vordingborg"},"dominica":{"file":"chunks/cities_dominica.json","count":1,"sample":"Roseau"},"dominican-republic":{"file":"chunks/cities_dominican-republic.json","count":49,"sample":"Villa Francisca"},"algeria":{"file":"chunks/cities_algeria.json","count":294,"sample":"Boumerdas"},"ecuador":{"file":"chunks/cities_ecuador.json","count":71,"sample":"Zamora"},"estonia":{"file":"chunks/cities_estonia.json","count":8,"sample":"Viljandi"},"egypt":{"file":"chunks/cities_egypt.json","count":236,"sample":"Zefta"},"western-sahara":{"file":"chunks/cities_western-sahara.json","count":4,"sample":"El Marsa"},"eritrea":{"file":"chunks/cities_eritrea.json","count":7,"sample":"Massawa"},"spain":{"file":"chunks/cities_spain.json","count":735,"sample":"Zubia"},"ethiopia":{"file":"chunks/cities_ethiopia.json","count":233,"sample":"Waal"},"finland":{"file":"chunks/cities_finland.json","count":103,"sample":"Yl\u00f6j\u00e4rvi"},"fiji":{"file":"chunks/cities_fiji.json","count":7,"sample":"Suva"},"falkland-islands-malvinas":{"file":"chunks/cities_falkland-islands-malvinas.json","count":1,"sample":"Stanley"},"micronesia-federated-states-of":{"file":"chunks/cities_micronesia-federated-states-of.json","count":1,"sample":"Palikir"},"faroe-islands":{"file":"chunks/cities_faroe-islands.json","count":1,"sample":"T\u00f3rshavn"},"france":{"file":"chunks/cities_france.json","count":692,"sample":"Yerres"},"gabon":{"file":"chunks/cities_gabon.json","count":15,"sample":"Tchibanga"},"united-kingdom":{"file":"chunks/cities_united-kingdom.json","count":864,"sample":"York"},"grenada":{"file":"chunks/cities_grenada.json","count":1,"sample":"Saint George's"},"georgia":{"file":"chunks/cities_georgia.json","count":17,"sample":"Zugdidi"},"french-guiana":{"file":"chunks/cities_french-guiana.json","count":5,"sample":"Saint-Laurent-du-Maroni"},"guernsey":{"file":"chunks/cities_guernsey.json","count":1,"sample":"Saint Peter Port"},"ghana":{"file":"chunks/cities_ghana.json","count":102,"sample":"Yendi"},"gibraltar":{"file":"chunks/cities_gibraltar.json","count":1,"sample":"Gibraltar"},"greenland":{"file":"chunks/cities_greenland.json","count":1,"sample":"Nuuk"},"gambia":{"file":"chunks/cities_gambia.json","count":33,"sample":"Welingara"},"guinea":{"file":"chunks/cities_guinea.json","count":47,"sample":"Yende Millimou"},"guadeloupe":{"file":"chunks/cities_guadeloupe.json","count":10,"sample":"Sainte-Rose"},"equatorial-guinea":{"file":"chunks/cities_equatorial-guinea.json","count":4,"sample":"Ebebiyin"},"greece":{"file":"chunks/cities_greece.json","count":115,"sample":"Vo\u00fala"},"south-georgia-and-the-south-sandwich-islands":{"file":"chunks/cities_south-georgia-and-the-south-sandwich-islands.json","count":1,"sample":"Grytviken"},"guatemala":{"file":"chunks/cities_guatemala.json","count":102,"sample":"Zaragoza"},"guam":{"file":"chunks/cities_guam.json","count":6,"sample":"Tamuning-Tumon-Harmon Village"},"guinea-bissau":{"file":"chunks/cities_guinea-bissau.json","count":4,"sample":"Xitole"},"guyana":{"file":"chunks/cities_guyana.json","count":3,"sample":"New Amsterdam"},"hong-kong":{"file":"chunks/cities_hong-kong.json","count":141,"sample":"Tsuen Wan"},"honduras":{"file":"chunks/cities_honduras.json","count":24,"sample":"Puerto Cortez"},"croatia":{"file":"chunks/cities_croatia.json","count":26,"sample":"Zapre\u0161i\u0107"},"haiti":{"file":"chunks/cities_haiti.json","count":30,"sample":"Verrettes"},"hungary":{"file":"chunks/cities_hungary.json","count":138,"sample":"\u00dajszeged"},"indonesia":{"file":"chunks/cities_indonesia.json","count":442,"sample":"Tongging"},"ireland":{"file":"chunks/cities_ireland.json","count":39,"sample":"Wexford"},"israel":{"file":"chunks/cities_israel.json","count":106,"sample":"Jerusalem"},"isle-of-man":{"file":"chunks/cities_isle-of-man.json","count":1,"sample":"Douglas"},"india":{"file":"chunks/cities_india.json","count":3776,"sample":"P\u016bnch"},"iraq":{"file":"chunks/cities_iraq.json","count":100,"sample":"Zaxo"},"iran-islamic-republic-of":{"file":"chunks/cities_iran-islamic-republic-of.json","count":406,"sample":"Lav\u0101s\u0101n"},"iceland":{"file":"chunks/cities_iceland.json","count":6,"sample":"Akureyri"},"italy":{"file":"chunks/cities_italy.json","count":656,"sample":"Vittoria"},"jersey":{"file":"chunks/cities_jersey.json","count":1,"sample":"Saint Helier"},"jamaica":{"file":"chunks/cities_jamaica.json","count":11,"sample":"Spanish Town"},"jordan":{"file":"chunks/cities_jordan.json","count":34,"sample":"W\u0101d\u012b as S\u012br"},"japan":{"file":"chunks/cities_japan.json","count":1297,"sample":"Shing\u016b"},"kenya":{"file":"chunks/cities_kenya.json","count":123,"sample":"Wote"},"kyrgyzstan":{"file":"chunks/cities_kyrgyzstan.json","count":31,"sample":"Suluktu"},"cambodia":{"file":"chunks/cities_cambodia.json","count":46,"sample":"Phnom Penh"},"kiribati":{"file":"chunks/cities_kiribati.json","count":1,"sample":"Tarawa"},"comoros":{"file":"chunks/cities_comoros.json","count":3,"sample":"Moutsamoudou"},"saint-kitts-and-nevis":{"file":"chunks/cities_saint-kitts-and-nevis.json","count":1,"sample":"Basseterre"},"korea-democratic-people-s-republic-of":{"file":"chunks/cities_korea-democratic-people-s-republic-of.json","count":97,"sample":"Y\u014fnan-\u016dp"},"korea-republic-of":{"file":"chunks/cities_korea-republic-of.json","count":147,"sample":"Heunghae"},"kuwait":{"file":"chunks/cities_kuwait.json","count":18,"sample":"Jan\u016bb as Surrah"},"cayman-islands":{"file":"chunks/cities_cayman-islands.json","count":2,"sample":"West Bay"},"kazakhstan":{"file":"chunks/cities_kazakhstan.json","count":83,"sample":"Zhanaozen"},"lao-people-s-democratic-republic":{"file":"chunks/cities_lao-people-s-democratic-republic.json","count":18,"sample":"Vientiane"},"lebanon":{"file":"chunks/cities_lebanon.json","count":18,"sample":"Zahl\u00e9"},"saint-lucia":{"file":"chunks/cities_saint-lucia.json","count":2,"sample":"Gros Islet"},"liechtenstein":{"file":"chunks/cities_liechtenstein.json","count":1,"sample":"Vaduz"},"sri-lanka":{"file":"chunks/cities_sri-lanka.json","count":60,"sample":"Welisara"},"liberia":{"file":"chunks/cities_liberia.json","count":16,"sample":"Zwedru"},"lesotho":{"file":"chunks/cities_lesotho.json","count":11,"sample":"Teyateyaneng"},"lithuania":{"file":"chunks/cities_lithuania.json","count":36,"sample":"Visaginas"},"luxembourg":{"file":"chunks/cities_luxembourg.json","count":3,"sample":"Luxembourg"},"latvia":{"file":"chunks/cities_latvia.json","count":15,"sample":"Valmiera"},"libya":{"file":"chunks/cities_libya.json","count":59,"sample":"Tobruk"},"morocco":{"file":"chunks/cities_morocco.json","count":179,"sample":"Smara"},"monaco":{"file":"chunks/cities_monaco.json","count":2,"sample":"Monte-Carlo"},"moldova-republic-of":{"file":"chunks/cities_moldova-republic-of.json","count":22,"sample":"Edine\u0163"},"montenegro":{"file":"chunks/cities_montenegro.json","count":8,"sample":"Podgorica"},"saint-martin-french-part":{"file":"chunks/cities_saint-martin-french-part.json","count":1,"sample":"Marigot"},"madagascar":{"file":"chunks/cities_madagascar.json","count":106,"sample":"Toamasina"},"marshall-islands":{"file":"chunks/cities_marshall-islands.json","count":2,"sample":"Majuro"},"north-macedonia":{"file":"chunks/cities_north-macedonia.json","count":38,"sample":"Zelino"},"mali":{"file":"chunks/cities_mali.json","count":60,"sample":"Z\u00e9goua"},"myanmar":{"file":"chunks/cities_myanmar.json","count":175,"sample":"Zigon"},"mongolia":{"file":"chunks/cities_mongolia.json","count":24,"sample":"Uliastay"},"macao":{"file":"chunks/cities_macao.json","count":6,"sample":"Taipa"},"northern-mariana-islands":{"file":"chunks/cities_northern-mariana-islands.json","count":1,"sample":"Saipan"},"martinique":{"file":"chunks/cities_martinique.json","count":8,"sample":"Saint-Joseph"},"mauritania":{"file":"chunks/cities_mauritania.json","count":26,"sample":"Zou\u00e9rat"},"montserrat":{"file":"chunks/cities_montserrat.json","count":2,"sample":"Plymouth"},"malta":{"file":"chunks/cities_malta.json","count":7,"sample":"\u017babbar"},"mauritius":{"file":"chunks/cities_mauritius.json","count":14,"sample":"Vacoas"},"maldives":{"file":"chunks/cities_maldives.json","count":1,"sample":"Male"},"malawi":{"file":"chunks/cities_malawi.json","count":23,"sample":"Karonga"},"mexico":{"file":"chunks/cities_mexico.json","count":643,"sample":"San Fernando"},"malaysia":{"file":"chunks/cities_malaysia.json","count":355,"sample":"Kuah"},"mozambique":{"file":"chunks/cities_mozambique.json","count":66,"sample":"Xai-Xai"},"namibia":{"file":"chunks/cities_namibia.json","count":19,"sample":"Ndiyona"},"new-caledonia":{"file":"chunks/cities_new-caledonia.json","count":3,"sample":"Noum\u00e9a"},"niger":{"file":"chunks/cities_niger.json","count":42,"sample":"Birnin Gaour\u00e9"},"norfolk-island":{"file":"chunks/cities_norfolk-island.json","count":1,"sample":"Kingston"},"nigeria":{"file":"chunks/cities_nigeria.json","count":263,"sample":"Zuru"},"nicaragua":{"file":"chunks/cities_nicaragua.json","count":37,"sample":"Tipitapa"},"netherlands":{"file":"chunks/cities_netherlands.json","count":242,"sample":"Zwolle"},"norway":{"file":"chunks/cities_norway.json","count":41,"sample":"Alta"},"nepal":{"file":"chunks/cities_nepal.json","count":46,"sample":"W\u0101li\u1e45"},"nauru":{"file":"chunks/cities_nauru.json","count":1,"sample":"Yaren"},"niue":{"file":"chunks/cities_niue.json","count":1,"sample":"Alofi"},"new-zealand":{"file":"chunks/cities_new-zealand.json","count":58,"sample":"Wellington"},"oman":{"file":"chunks/cities_oman.json","count":27,"sample":"Sur"},"panama":{"file":"chunks/cities_panama.json","count":27,"sample":"Veracruz"},"peru":{"file":"chunks/cities_peru.json","count":136,"sample":"Yurimaguas"},"french-polynesia":{"file":"chunks/cities_french-polynesia.json","count":3,"sample":"Punaauia"},"papua-new-guinea":{"file":"chunks/cities_papua-new-guinea.json","count":13,"sample":"Wewak"},"philippines":{"file":"chunks/cities_philippines.json","count":530,"sample":"Zumarraga"},"pakistan":{"file":"chunks/cities_pakistan.json","count":363,"sample":"Sharifabad"},"poland":{"file":"chunks/cities_poland.json","count":363,"sample":"\u017byrard\u00f3w"},"saint-pierre-and-miquelon":{"file":"chunks/cities_saint-pierre-and-miquelon.json","count":1,"sample":"Saint-Pierre"},"pitcairn":{"file":"chunks/cities_pitcairn.json","count":1,"sample":"Adamstown"},"puerto-rico":{"file":"chunks/cities_puerto-rico.json","count":21,"sample":"Aguadilla"},"palestine-state-of":{"file":"chunks/cities_palestine-state-of.json","count":45,"sample":"Rafa\u1e29"},"portugal":{"file":"chunks/cities_portugal.json","count":179,"sample":"Vila Franca de Xira"},"palau":{"file":"chunks/cities_palau.json","count":1,"sample":"Ngerulmud"},"paraguay":{"file":"chunks/cities_paraguay.json","count":28,"sample":"Yby Ya\u00fa"},"qatar":{"file":"chunks/cities_qatar.json","count":26,"sample":"Al \u2018Unayzah"},"r-union":{"file":"chunks/cities_r-union.json","count":14,"sample":"Saint-Pierre"},"romania":{"file":"chunks/cities_romania.json","count":134,"sample":"Zimnicea"},"serbia":{"file":"chunks/cities_serbia.json","count":50,"sample":"Zrenjanin"},"russian-federation":{"file":"chunks/cities_russian-federation.json","count":1109,"sample":"Udomlya"},"rwanda":{"file":"chunks/cities_rwanda.json","count":45,"sample":"Rwamagana"},"saudi-arabia":{"file":"chunks/cities_saudi-arabia.json","count":96,"sample":"Yanbu"},"solomon-islands":{"file":"chunks/cities_solomon-islands.json","count":7,"sample":"Panatina"},"seychelles":{"file":"chunks/cities_seychelles.json","count":1,"sample":"Victoria"},"sudan":{"file":"chunks/cities_sudan.json","count":75,"sample":"Dongola"},"sweden":{"file":"chunks/cities_sweden.json","count":109,"sample":"Ume\u00e5"},"singapore":{"file":"chunks/cities_singapore.json","count":65,"sample":"Yio Chu Kang"},"saint-helena-ascension-and-tristan-da-cunha":{"file":"chunks/cities_saint-helena-ascension-and-tristan-da-cunha.json","count":1,"sample":"Jamestown"},"slovenia":{"file":"chunks/cities_slovenia.json","count":9,"sample":"Trbovlje"},"svalbard-and-jan-mayen":{"file":"chunks/cities_svalbard-and-jan-mayen.json","count":1,"sample":"Longyearbyen"},"slovakia":{"file":"chunks/cities_slovakia.json","count":61,"sample":"Vranov nad Top\u013eou"},"sierra-leone":{"file":"chunks/cities_sierra-leone.json","count":14,"sample":"Waterloo"},"san-marino":{"file":"chunks/cities_san-marino.json","count":1,"sample":"San Marino"},"senegal":{"file":"chunks/cities_senegal.json","count":70,"sample":"Ziguinchor"},"somalia":{"file":"chunks/cities_somalia.json","count":41,"sample":"Wanlaweyn"},"suriname":{"file":"chunks/cities_suriname.json","count":12,"sample":"Rainville"},"south-sudan":{"file":"chunks/cities_south-sudan.json","count":16,"sample":"Yei"},"sao-tome-and-principe":{"file":"chunks/cities_sao-tome-and-principe.json","count":1,"sample":"S\u00e3o Tom\u00e9"},"el-salvador":{"file":"chunks/cities_el-salvador.json","count":35,"sample":"Zacatecoluca"},"sint-maarten-dutch-part":{"file":"chunks/cities_sint-maarten-dutch-part.json","count":1,"sample":"Philipsburg"},"syrian-arab-republic":{"file":"chunks/cities_syrian-arab-republic.json","count":88,"sample":"Z\u0101k\u012byah"},"eswatini":{"file":"chunks/cities_eswatini.json","count":3,"sample":"Mbabane"},"turks-and-caicos-islands":{"file":"chunks/cities_turks-and-caicos-islands.json","count":2,"sample":"Cockburn Town"},"chad":{"file":"chunks/cities_chad.json","count":46,"sample":"Iriba"},"french-southern-territories":{"file":"chunks/cities_french-southern-territories.json","count":1,"sample":"Port-aux-Fran\u00e7ais"},"togo":{"file":"chunks/cities_togo.json","count":20,"sample":"Vogan"},"thailand":{"file":"chunks/cities_thailand.json","count":327,"sample":"Ban Talat Yai"},"tajikistan":{"file":"chunks/cities_tajikistan.json","count":31,"sample":"Yovon"},"timor-leste":{"file":"chunks/cities_timor-leste.json","count":10,"sample":"Suai"},"turkmenistan":{"file":"chunks/cities_turkmenistan.json","count":34,"sample":"Balkanabat"},"tunisia":{"file":"chunks/cities_tunisia.json","count":126,"sample":"Zaouiet Sousse"},"tonga":{"file":"chunks/cities_tonga.json","count":1,"sample":"Nuku\u2018alofa"},"t-rkiye":{"file":"chunks/cities_t-rkiye.json","count":424,"sample":"Y\u00fcksekova"},"trinidad-and-tobago":{"file":"chunks/cities_trinidad-and-tobago.json","count":14,"sample":"Tunapuna"},"tuvalu":{"file":"chunks/cities_tuvalu.json","count":1,"sample":"Funafuti"},"taiwan-province-of-china":{"file":"chunks/cities_taiwan-province-of-china.json","count":66,"sample":"Douliu"},"tanzania-united-republic-of":{"file":"chunks/cities_tanzania-united-republic-of.json","count":224,"sample":"Zanzibar"},"ukraine":{"file":"chunks/cities_ukraine.json","count":374,"sample":"Lebedyn"},"uganda":{"file":"chunks/cities_uganda.json","count":141,"sample":"Yumbe"},"united-states":{"file":"chunks/cities_united-states.json","count":3398,"sample":"Fort Hunt"},"uruguay":{"file":"chunks/cities_uruguay.json","count":31,"sample":"Young"},"uzbekistan":{"file":"chunks/cities_uzbekistan.json","count":112,"sample":"Nukus"},"holy-see-vatican-city-state":{"file":"chunks/cities_holy-see-vatican-city-state.json","count":1,"sample":"Vatican City"},"saint-vincent-and-the-grenadines":{"file":"chunks/cities_saint-vincent-and-the-grenadines.json","count":2,"sample":"Kingstown"},"venezuela-bolivarian-republic-of":{"file":"chunks/cities_venezuela-bolivarian-republic-of.json","count":216,"sample":"La Guardia"},"virgin-islands-british":{"file":"chunks/cities_virgin-islands-british.json","count":1,"sample":"Road Town"},"virgin-islands-u-s":{"file":"chunks/cities_virgin-islands-u-s.json","count":2,"sample":"Charlotte Amalie"},"viet-nam":{"file":"chunks/cities_viet-nam.json","count":290,"sample":"Y\u00ean Vinh"},"vanuatu":{"file":"chunks/cities_vanuatu.json","count":1,"sample":"Port-Vila"},"wallis-and-futuna":{"file":"chunks/cities_wallis-and-futuna.json","count":1,"sample":"Mata-Utu"},"samoa":{"file":"chunks/cities_samoa.json","count":1,"sample":"Apia"},"no-country-found-for-alpha-2-code-xk":{"file":"chunks/cities_no-country-found-for-alpha-2-code-xk.json","count":21,"sample":"Zve\u010dan"},"yemen":{"file":"chunks/cities_yemen.json","count":25,"sample":"Zinjib\u0101r"},"mayotte":{"file":"chunks/cities_mayotte.json","count":6,"sample":"Mamoudzou"},"south-africa":{"file":"chunks/cities_south-africa.json","count":304,"sample":"Roodepoort"},"zambia":{"file":"chunks/cities_zambia.json","count":77,"sample":"Nchelenge"},"zimbabwe":{"file":"chunks/cities_zimbabwe.json","count":30,"sample":"Zvishavane"}}